Workbook

Sheet Read Me
A1: PILLAR 4 - US STOCK NOTES
A3: What this is | B3: Every comment Claude has written about each stock in the US dashboard, kept in one place so you and Dad can re-read the reasoning instead of asking the same question twice.
A4: Generated | B4: 2026-09-19
A5: Objective on record | B5: SL-P4: 100% capital gain over five years, 2026-2030 (about 15% a year).
A7: SHEET | B7: WHAT IS IN IT
A8: Stock Index | B8: One row per ticker: a plain-English line on WHAT THE COMPANY DOES, then when it was founded, its headquarters, employee count, and separate OPERATIONS and VISION notes - followed by group, whether you hold it, shares, cost, budget, last price and the most recent thing Claude said about it. Start here.
A9: Comment Log | B9: Executive summaries, one row per stock per week (Monday-Sunday). GREEN text = something positive, RED text = a risk or negative view, bold RED FLAG = urgent warning. The View column gives the week's overall tilt at a glance.
A10: Full Log | B10: The complete unabridged archive - every individual comment with its exact date, for when the summary is not enough.
A11: Dashboard Notes | B11: The dated technical notes stored inside the dashboard itself - data conflicts, earnings dates, warnings, what was verified and what was not. Longer and more detailed than the chat comments.
A12: Our Notes | B12: YOURS. Claude never overwrites this sheet - it is read back and carried forward on every rebuild. Put your own observations, Dad's notes, and decisions here.
A13: Follow-ups | B13: Open items Claude is carrying: unanswered offers, data to fix, earnings to watch.
A15: HOW TO LOOK UP ONE STOCK
A16: 1 | B16: Go to the Comment Log sheet.
A17: 2 | B17: Click the small arrow in the Ticker header (row 1, column A).
A18: 3 | B18: Untick "Select All", tick just the ticker you want, press OK.
A19: 4 | B19: Every comment about that stock, oldest to newest, is now on screen.
A20: 5 | B20: To clear it, click the arrow again and tick "Select All".
A22: IMPORTANT LIMITS
A23: Not advice | B23: These are analytical comments, not licensed investment advice. Every order is placed by Salee.
A24: Comments age | B24: A comment is a snapshot of what was true and known on its date. A buy case from three weeks ago may have been overtaken by an earnings report. Always check the date column.
A25: Prices are closes | B25: Prices in the Stock Index come from the dashboard and are closing prices with a stated date, not live quotes.
A26: Coverage | B26: Comments were mined from the chat history of the Jul 20 - Aug 7 2026 session plus the full git history of the dashboard. Anything said before that session is not captured.

Sheet Stock Index
A1: Ticker | B1: Company | C1: What the company does | D1: Founded | E1: Headquarters | F1: Employees | G1: Operations | H1: Vision | I1: Group | J1: Held | K1: Shares | L1: Cost (USD) | M1: Budget (USD) | N1: Last close (USD) | O1: Price date | P1: Comments | Q1: First comment | R1: Last comment | S1: Most recent comment
A2: AMZN | B2: Amazon | C2: Online shopping giant, and the world's largest cloud-computing provider (AWS). | D2: 1994 | E2: Washington, United States | F2: 1,576,000 | G2: Runs online and physical shops in North America and other countries, plus a large computing-rental arm and its own devices such as Kindle and Echo. | H2: To sell consumer goods, advertising and subscriptions through online and physical stores in North America and internationally. | I2: Hyperscalers & Model Owners | J2: YES | K2: 209 | L2: 48600.75 | M2: 48000 | N2: 251.19 | O2: 2026-09-17 | P2: =COUNTIF('Full Log'!$A:$A,$A2) | Q2: 2026-07-20 | R2: 2026-09-17 | S2: Your AMZN buy is logged. 7 shares @ $285.3599 (limit 285.50, order 65487), $1,997.52 + $8.56 fees = $2,006.08. You now hold 209 shares at an average cost of $232.54, worth $59,360 — up 22.1%. Budget left in the Amazon sleeve: $1,399.25, so that position is now essentially full.
A3: GOOGL | B3: Alphabet | C3: Google search and YouTube advertising, plus Google Cloud and Waymo self-driving cars. | D3: 1998 | E3: California, United States | F3: 190,820 | G3: Runs search, advertising, phone software, video and email services across the Americas, Europe, Africa, the Middle East and Asia, plus a computing-rental arm. | H3: To offer a wide range of internet products and platforms, grouped into its main services, its computing-rental business and smaller ventures. | I3: Hyperscalers & Model Owners | J3: YES | K3: 217 | L3: 59475.92 | M3: 78000 | N3: 347.33 | O3: 2026-09-17 | P3: =COUNTIF('Full Log'!$A:$A,$A3) | Q3: 2026-07-20 | R3: 2026-09-18 | S3: First — a useful discovery about your broker. I checked whether the "Current Price" column in your POEMS screen was a live intraday quote or the official close, because it matters for the dashboard's integrity. I tested four names against an independent source: MSFT $487.65, META $590.24, TSM $406.11, GOOGL $373.51 — all four matched to the cent. That column is the official close. It means your POEMS screenshot is a legitimate price source for the whole held book, and future updates get much faster.
A4: META | B4: Meta Platforms | C4: Facebook, Instagram and WhatsApp — sells advertising to their billions of users. | D4: 2004 | E4: California, United States | F4: 78,865 | G4: Runs Facebook, Instagram, WhatsApp and Messenger, plus a division making virtual-reality headsets and smart glasses, serving users in most world regions. | H4: To build products that let people connect and share with friends and family through phones, computers, headsets and smart glasses. | I4: Hyperscalers & Model Owners | J4: YES | K4: 59.5 | L4: 39239.51 | M4: 52000 | N4: 682.31 | O4: 2026-09-17 | P4: =COUNTIF('Full Log'!$A:$A,$A4) | Q4: 2026-07-20 | R4: 2026-09-17 | S4: Your six buys from last night are in. FN 3 sh @ $532.00, LITE 2 sh @ $854.68, META 3.5 sh @ $583.24, COHR 4 sh @ $330.00, AAOI 10 sh @ $133.00 — $8,039.48 total. Every fill price was reverse-engineered from the cash amounts, and they all came out to clean round limit prices with a flat $8.56 commission, which is exactly what POEMS charges. Your new cost basis of $560,431.70 matches the POEMS statement to the cent.
A5: MSFT | B5: Microsoft | C5: Windows and Office software, Azure cloud computing, and a large stake in OpenAI. | D5: 1975 | E5: Washington, United States | F5: 223,000 | G5: Sells office and business software, rented computing power, Windows, game consoles and search advertising to people and companies worldwide. | H5: To develop and support a broad set of technology products and services for individuals and businesses around the world. | I5: Hyperscalers & Model Owners | J5: YES | K5: 117 | L5: 52878.96 | M5: 58000 | N5: 497.75 | O5: 2026-09-17 | P5: =COUNTIF('Full Log'!$A:$A,$A5) | Q5: 2026-07-20 | R5: 2026-09-17 | S5: - VEEV's return-on-capital reads 176% on one source and 31% on another. I stored the conservative 31.44%. The 176% is a maths artifact — Veeva has almost no debt and a tiny capital base, so the ratio explodes. Don't read it as "six times better than Microsoft."
A6: AMBA | B6: Ambarella | I6: AI Chips & Chip Design | N6: 64.33 | O6: 2026-09-15 | P6: =COUNTIF('Full Log'!$A:$A,$A6) | Q6: 2026-08-19 | R6: 2026-09-09 | S6: Sep 9, 2026: AMBARELLA (AMBA) ADDED TO THE BOARD AS AN UNFUNDED WATCH ROW WITH A REJECT VERDICT, at Salee's instruction to record the research rather than repeat it. Group 1, budget 0, nothing bought. Edge-AI vision SoCs, 50m+ AI units installed, price 63.48 and 34.4% below its 96.69 high. ⚠️ REJECTED ON THREE COUNTS: revenue growth decelerating four quarters running to 13.2%; GAAP loss-making in each of the last five quarters with trailing net income -56.32m; and stock compensation running at 21% of revenue, larger than the entire non-GAAP profit. Add a single distributor at 60.2% of revenue and a forward P/E of 71.49. It fails both screens Salee approved this week - the under-15% growth cut of Sep 7 and the loss-making cut of Sep 8.
A7: AMD | B7: Advanced Micro Devices | C7: Designs computer processors and AI chips — Nvidia's main challenger. | D7: 1969 | E7: California, United States | F7: 31,000 | G7: Designs chips sold internationally through three business lines: data centres, personal computers and gaming, and equipment with chips built in. | H7: To supply processors, graphics chips and artificial-intelligence hardware for business and consumer computing worldwide. | I7: AI Chips & Chip Design | J7: YES | K7: 55 | L7: 13789.22 | M7: 24000 | N7: 545.09 | O7: 2026-09-17 | P7: =COUNTIF('Full Log'!$A:$A,$A7) | Q7: 2026-07-21 | R7: 2026-09-18 | S7: > Conviction: High — but on *valuation and position discipline*, not on "NVDA always goes up." > > Horizon: Long (2+ years) — this fits the 2026–2030 doubling objective. > > What would change my mind: (1) Aug 26 earnings guiding below ~$91B or gross margin slipping under 73% — that would say the pricing power is cracking; (2) any sign the hyperscalers are cutting 2027 capex plans; (3) NVDA rising above ~$260 before earnings, which would put it at a forward multiple where the cheapness argument stops working; (4) SpaceX or another marquee customer publicly dual-sourcing to AMD or in-house silicon.
A8: ARM | B8: Arm Holdings | C8: Licenses the chip blueprints used inside nearly every smartphone in the world. | D8: 1990 | E8: United Kingdom | F8: 9,584 | G8: Licenses chip blueprints rather than making chips, serving chipmakers, device makers and computing-rental firms for phones, cars and data centres. | H8: To research, develop and license chip designs, software and tools that other companies use to build their own chips. | I8: AI Chips & Chip Design | N8: 241.83 | O8: 2026-09-15 | P8: =COUNTIF('Full Log'!$A:$A,$A8) | Q8: 2026-07-21 | R8: 2026-09-18 | S8: Portfolio now: $560,432 cost, $683,857 market value, +$123,426 (+22.02%). A strong day across the board — 109 of 112 names repriced, and the tone was risk-on: PLTR +29%, AAOI +19%, ARM +17%, FN +16%, your own AMD +7% and AVGO +6.6%.
A9: AVGO | B9: Broadcom | C9: Custom AI chips and networking parts, plus a large enterprise software business. | D9: 1961 | E9: California, United States | F9: 33,000 | G9: Supplies chips and business software internationally through two arms: semiconductor products and infrastructure software. | H9: To design and supply the chips and software that run company networks, data centres, telephone systems and broadband. | I9: AI Chips & Chip Design | J9: YES | K9: 88.5 | L9: 30125.18 | M9: 50000 | N9: 347.3 | O9: 2026-09-17 | P9: =COUNTIF('Full Log'!$A:$A,$A9) | Q9: 2026-07-23 | R9: 2026-09-16 | S9: Portfolio now: $560,432 cost, $683,857 market value, +$123,426 (+22.02%). A strong day across the board — 109 of 112 names repriced, and the tone was risk-on: PLTR +29%, AAOI +19%, ARM +17%, FN +16%, your own AMD +7% and AVGO +6.6%.
A10: CDNS | B10: Cadence Design Systems | C10: The software that engineers use to design computer chips. | D10: 1988 | E10: California, United States | F10: 13,800 | G10: Sells software, testing hardware and ready-made circuit designs to electronics and chip makers, and works in partnership with NVIDIA. | H10: To provide the software, hardware and design building blocks that engineers use to design computer chips and electronic systems. | I10: AI Chips & Chip Design | J10: YES | K10: 12 | L10: 3918.01 | N10: 280.76 | O10: 2026-09-17 | P10: =COUNTIF('Full Log'!$A:$A,$A10) | Q10: 2026-07-21 | R10: 2026-09-17 | S10: The practical cadence. Fundamentals refresh when a company files, not on a clock. For your US names that means roughly four times a year each. The revenue and EPS you'd read off TradingView on a Tuesday are identical to Monday's unless that company reported in between. So it's an event-driven feed, not a daily one.
A11: MCHP | B11: Microchip Technology | C11: Microcontrollers and analog chips for cars, factory equipment and data centres. | D11: 1989 | E11: Arizona, United States | F11: 17,900 | G11: Makes and sells small control chips across the Americas, Europe and Asia through two arms: semiconductor products and technology licensing. | H11: To develop, make and sell smart, connected and secure control chips that sit inside other companies' equipment. | I11: AI Chips & Chip Design | N11: 71.49 | O11: 2026-09-15 | P11: =COUNTIF('Full Log'!$A:$A,$A11) | Q11: 2026-08-09 | R11: 2026-08-09 | S11: Aug 8 addition: MCHP (Microchip Technology, NASDAQ) added to Computing Chips at the Aug 7, 2026 close 84.69, UP 13.89% that day, stamp 'At close: Aug 7, 2026, 4:00 PM EDT', second-sourced by MarketBeat. Watchlist only - no position, no budget. Microchip makes microcontrollers, analog and connectivity chips for cars, industry, aerospace/defence and data centres, and is RECOVERING from a deep inventory-correction downcycle. Q1 FY2027 (ended Jun 30, reported Aug 6) was a clear beat and the trigger for the pop: net sales 1.485B (+38% YoY, +13% QoQ), GAAP EPS 0.37 (vs a loss a year ago), non-GAAP EPS 0.76; Q2 guidance strong (~1.6B, +41% YoY); inventory days improving (185->175); PCIe Gen 6 / data-centre commentary cited. Pays a ~2.15% dividend (0.455/qtr). KEY VALUATION NOTE: trailing P/E 124.83 and payout ratio 268% look alarming but are DISTORTED by trough earnings during the downturn - ...
A12: MPWR | B12: Monolithic Power | C12: Power-management chips that feed clean, steady voltage to AI processors. | D12: 1997 | E12: Florida, United States | F12: 4,501 | G12: Designs power-management chips used in data centre servers, cars, appliances and networks, sold through distributors in China, Taiwan, Korea, Europe, the US and Japan. | H12: To supply the semiconductor parts that convert and control electrical power inside electronic systems. | I12: AI Chips & Chip Design | N12: 1142.46 | O12: 2026-09-15 | P12: =COUNTIF('Full Log'!$A:$A,$A12) | Q12: 2026-07-21 | R12: 2026-09-12 | S12: The picture got further away, not closer. Amazon jumped 15% and Monolithic Power 10.6% overnight — both blew straight through your limits. Google added 4.6%. Nothing moved toward you except Micron and Coinbase, and both are still short of the mark. ISRG remains the nearest at 5.6%, and it's drifting your way rather than away.
A13: MRVL | B13: Marvell Technology | C13: Custom data-centre chips that move data between AI servers. | D13: 1995 | E13: Delaware, United States | F13: 7,480 | G13: Designs data-centre and networking chips, with operations in the United States, Argentina, China, India, Israel, Japan, Singapore, South Korea, Taiwan and Vietnam. | H13: To supply the chips that move and store data from the heart of large data centres out to the edge of networks. | I13: AI Chips & Chip Design | J13: YES | K13: 48.5 | L13: 7872.66 | M13: 21000 | N13: 240.76 | O13: 2026-09-17 | P13: =COUNTIF('Full Log'!$A:$A,$A13) | Q13: 2026-07-22 | R13: 2026-09-16 | S13: ⚠ But I have to challenge your own note, because you wrote two things that conflict. Your price limits say "buy RKLB." Your *new valuation measures* — Price/FCF ≤ 10× and EV/EBITDA < 10 — say buy none of these. RKLB has negative free cash flow and no meaningful EBITDA; it fails both screens by a mile. So do CRDO, MRVL, and ONDS. Those deep-value gates (P/FCF ≤10, EV/EBITDA <10) are built for mature cash machines — they will *permanently* exclude every growth/space/AI name on this list. You can run a price-limit discipline *or* a hard value screen, but not both on the same tickers. Decide which game each name is playing before you buy, or you'll never pull the trigger on anything.
A14: NVDA | B14: NVIDIA | C14: Makes the GPU chips that almost all AI computing runs on. | D14: 1993 | E14: California, United States | F14: 42,000 | G14: Sells computing and graphics chips through two arms, with operations in the United States, Taiwan, China, Hong Kong and Europe. | H14: To operate as a company that supplies the computing equipment whole data centres use for artificial intelligence. | I14: AI Chips & Chip Design | J14: YES | K14: 420 | L14: 79380.28 | M14: 95000 | N14: 219.34 | O14: 2026-09-17 | P14: =COUNTIF('Full Log'!$A:$A,$A14) | Q14: 2026-07-20 | R14: 2026-09-19 | S14: - SpaceX went exclusive. Announced Aug 5: SpaceX is building its "Starmind" AI system *exclusively* on NVIDIA chips (Vera CPUs, Rubin GPUs). Musk called the architecture "the best." SpaceX targets 10 gigawatts of computing power by end-2027 and says it'll take "a very significant percentage" of NVIDIA's GPUs next year. This is a brand-new customer at a scale that barely existed six months ago.
A15: QCOM | B15: Qualcomm | C15: Smartphone processors and modems, expanding into cars and AI laptops. | D15: 1985 | E15: California, United States | F15: 52,000 | G15: Runs three arms worldwide: chip products, patent licensing and start-up investing, plus government services and data-centre products. | H15: To develop and commercialise the basic technologies that the wireless telephone industry depends on. | I15: AI Chips & Chip Design | N15: 187.8 | O15: 2026-09-15 | P15: =COUNTIF('Full Log'!$A:$A,$A15) | Q15: 2026-08-18 | R15: 2026-09-15 | S15: 💡 CASH RECONCILES TO THREE CENTS ON 236,000 DOLLARS. The 11 September balance of 227,203.00, plus the four settlements forecast that day (+3,677.68), plus ZETA, QCOM and the dividend, gives 236,324.20 against the 236,324.23 POEMS shows. THE FORECAST MADE ON 11 SEPTEMBER WAS RIGHT. ⚠️ THURSDAY 17 SEPTEMBER COMMITS 46,526.13 OF IT to six tranches, leaving about 189,798.
A16: SNPS | B16: Synopsys | I16: AI Chips & Chip Design | M16: 13000 | N16: 367.7 | O16: 2026-09-15 | P16: =COUNTIF('Full Log'!$A:$A,$A16) | Q16: 2026-08-17 | R16: 2026-09-18 | S16: ACTION: WRITE THE ZERO-OIL DECISION DOWN - either a deliberate exclusion or an unintended gap. Either answer is fine; having no answer is the same absence-of-a-decision fault as ARM, SNPS, LHX, APP and SE.
A17: AMAT | B17: Applied Materials | C17: Equipment that deposits and etches the microscopic layers inside every chip. | D17: 1967 | E17: California, United States | F17: 36,500 | G17: Supplies chip factory equipment, services and software in the United States, China, Korea, Taiwan, Japan, Southeast Asia and Europe, through two business arms. | H17: To provide the equipment, services and know-how that chipmakers use to build semiconductors. | I17: Foundry, Equipment & Test | J17: YES | K17: 38 | L17: 10086.63 | M17: 22000 | N17: 417.4 | O17: 2026-09-17 | P17: =COUNTIF('Full Log'!$A:$A,$A17) | Q17: 2026-07-20 | R17: 2026-09-19 | S17: Why it inflected. On July 29 AXT signed a supply agreement with Lumentum — that's LITE, already in this same group — running to end-2031. Lumentum pays $43.5M up front and another $43.5M in 2028, $87M total, applied as credits against reserved wafer capacity. That is a customer pre-paying for years of flour. The very next day AXT reported Q2 with adjusted earnings of $0.19 against $0.07 expected — nearly triple. Gross margin jumped from the low-30s to 44.9%.
A18: AMKR | B18: Amkor Technology | C18: Packages and tests finished chips on behalf of other chip companies. | D18: 1968 | E18: Arizona, United States | F18: 30,800 | G18: Packages and tests finished chips for other companies, with operations in the United States, Japan, Europe and the Asia-Pacific region. | H18: To handle the final packaging and testing steps for chipmakers, device makers and factories that do not do this work themselves. | I18: Foundry, Equipment & Test | N18: 46.38 | O18: 2026-09-15 | P18: =COUNTIF('Full Log'!$A:$A,$A18) | Q18: 2026-07-21 | R18: 2026-09-18 | S18: Worth noting on the close: MU finished at $820.53, +35.89%, recovering above where it traded intraday — the market did not fully buy the CXMT supply-glut story. The real damage on the book is older wounds, not Jul 28: AMKR −27.26%, ORCL −27.85%, TSLA −28.58%.
A19: ASML | B19: ASML Holding | C19: The only company that makes the EUV machines needed for the most advanced chips. | D19: 1984 | E19: Netherlands | F19: 44,175 | G19: Sells, upgrades and services the machines that print circuit patterns onto chips, supporting chipmakers across Asia, Europe and North America. | H19: To provide the advanced printing, measuring and inspection machines that chipmakers need to produce semiconductors. | I19: Foundry, Equipment & Test | J19: YES | K19: 13 | L19: 16394.06 | M19: 41000 | N19: 1629.67 | O19: 2026-09-17 | P19: =COUNTIF('Full Log'!$A:$A,$A19) | Q19: 2026-07-22 | R19: 2026-09-19 | S19: One honest limitation. I can only use logos that come from an open, freely-licensed icon library that I can install into this workspace; I can't pull company logos off the internet from here, and most chip and industrial companies never released a free version of their mark. So nine of the twenty are the real brandmarks — NVDA, GOOGL, AMZN, MSFT, META, AVGO, AMD, AAPL and PANW. The other eleven — TSM, MU, ASML, AMAT, ANET, ISRG, CRDO, MRVL, ETN, CRWD and ORCL — get a ticker monogram in exactly the same gold-ringed disc.
A20: INTC | B20: Intel | C20: The historic US chipmaker, now rebuilding both its chip designs and its factories. | D20: 1968 | E20: California, United States | F20: 85,100 | G20: Designs and manufactures chips, with operations in the United States, Ireland and Israel, run as three units including a factory arm making chips for others. | H20: To design, make and sell computing products, and to build a manufacturing business that produces chips for other companies. | I20: Foundry, Equipment & Test | J20: YES | K20: 25 | L20: 1127.56 | N20: 108.8 | O20: 2026-09-17 | P20: =COUNTIF('Full Log'!$A:$A,$A20) | Q20: 2026-07-21 | R20: 2026-09-17 | S20: > Conviction: High. Horizon: Long (3–5 years, fits the 2030 mandate). What would change my mind: a serious Taiwan Strait escalation, or evidence that Intel or Samsung has genuinely closed the leading-edge manufacturing gap.
A21: KLAC | B21: KLA Corporation | C21: Inspection machines that find microscopic defects on chips during manufacturing. | D21: 1975 | E21: California, United States | F21: 15,200 | G21: Runs three business lines making inspection and measuring machines for chip and circuit-board plants, sold worldwide. | H21: Aims to help chip makers find and fix flaws early so more of what they build works properly. | I21: Foundry, Equipment & Test | J21: YES | K21: 18 | L21: 3510.69 | M21: 14000 | N21: 168.98 | O21: 2026-09-17 | P21: =COUNTIF('Full Log'!$A:$A,$A21) | Q21: 2026-07-22 | R21: 2026-09-18 | S21: Also, the Jul 31 earnings cron landed while the container was rolled back: AAPL, AMZN, COIN, MA, plus a KLAC catch-up. Two worth your attention — AMZN's $5.75 Q2 EPS includes a $53.4B pre-tax Anthropic mark-up, so the board stores underlying TTM EPS of 8.61 ex-gain; and COIN's TTM has turned loss-making, which nulled its P/E, forward P/E, PEG, EV/EBITDA and Rule-40.
A22: LRCX | B22: Lam Research | C22: Etching and deposition equipment, especially important for advanced memory chips. | D22: 1980 | E22: California, United States | F22: 17,200 | G22: Builds, services and refurbishes chip-making machines, selling into the United States, China, Korea, Taiwan, Japan, Southeast Asia and Europe. | H22: Aims to supply the machines that lay down, carve and clean the layers used to build computer chips. | I22: Foundry, Equipment & Test | J22: YES | K22: 22 | L22: 4100.12 | M22: 16000 | N22: 269.31 | O22: 2026-09-17 | P22: =COUNTIF('Full Log'!$A:$A,$A22) | Q22: 2026-07-20 | R22: 2026-09-19 | S22: I want to be fair to it, because it's the most interesting of the three rejects. AirJoule has a 50/50 joint venture with GE Vernova that is genuinely operating — they installed a unit at GE Vernova's research campus in New York on July 28. Kubota signed them as exclusive US residential partner on July 21 (the stock jumped 15% that day). They have $35M cash and no debt, funded into 2028. All five analysts covering it have targets above the current price — the lowest target, $6.00, sits above the $5.95 price.
A23: TER | B23: Teradyne | C23: Machines that test finished chips, plus industrial and collaborative robots. | D23: 1960 | E23: Massachusetts, United States | F23: 6,600 | G23: Designs and sells machines that test computer chips, and also makes robots, operating in the United States, Asia Pacific, Europe, the Middle East and Africa. | H23: To supply the testing equipment that checks chips work properly, plus robots that work alongside people in factories. | I23: Foundry, Equipment & Test | J23: YES | K23: 10 | L23: 3567.37 | N23: 353.13 | O23: 2026-09-17 | P23: =COUNTIF('Full Log'!$A:$A,$A23) | Q23: 2026-07-22 | R23: 2026-09-18 | S23: AEHR → move from Group 1 to Group 2. ⚠️ It's misfiled today. AEHR sits in *Computing Chips* but it doesn't make chips — it makes wafer-level burn-in and test *equipment*. It belongs in Group 2, Chips Manufacturing, alongside ASML, AMAT, LRCX and KLAC, which is exactly its peer set. While we're in there: TER (Teradyne) is also misfiled, sitting in Group 6 (Robotic/Automation/EV). Teradyne's revenue is overwhelmingly semiconductor test; the robotics arm is the minority. It should move to Group 2 as well, so all the semi-cap equipment sits together and dad can see his true test-and-tools exposure in one row.
A24: TSEM | B24: Tower Semiconductor | C24: Tower Semiconductor is a contract chip manufacturer - a foundry - but unlike the giants chasing the smallest, fastest digital chips, Tower specialises in analog and specialty chips: parts that handle radio signals, electrical power, light and sensing. Its customers are other chip companies and system makers who design the chips and pay Tower to build them, for use in mobile phones, data-centre optical networking gear, cars, industrial equipment and medical devices. | D24: 1993 | E24: Migdal Haemek, Israel | F24: 5,613 | G24: Runs wafer fabrication plants in Israel, the United States, Japan and Italy, and in July 2026 announced a roughly 3 billion dollar capacity expansion in Japan with Japanese government (METI) support. Q2 2026 revenue mix: RF Infrastructure 25 percent, RF Mobile 23 percent, Power 17 percent, Sensors and Displays 15 percent, Discrete 11 percent, mixed-signal/CMOS and other 9 percent. Listed on NASDAQ since October 1994 and dual-listed in Tel Aviv. | H24: To be the analog specialty foundry of choice, and in particular to become a leading supplier of silicon photonics for AI data centres - management has taken that business from a 180 million dollar annualised run rate in Q2 2025 to 680 million in Q2 2026, targets 1 billion annualised by Q4 2026, has 1.3 billion of signed silicon photonics contracts for 2027, and has raised its 2028 model to 3.6 billion of revenue which it describes as fully spoken for by customers. | I24: Foundry, Equipment & Test | N24: 195.12 | O24: 2026-09-15 | P24: =COUNTIF('Full Log'!$A:$A,$A24) | Q24: 2026-08-11 | R24: 2026-09-14 | S24: (5) DECISION: NO BUDGET CHANGES, NOTHING BOUGHT OR SOLD, GROUP 4 STAYS AT 83,000. CIEN IS TRACKED, NOT FUNDED. Conviction HIGH. ⚠️ WHAT WOULD CHANGE MY MIND ON CIEN: two consecutive quarters of revenue growth above 25% WITH GAAP operating margin holding above 15% - that would make it the only profitable pure optical-systems company on the board and worth displacing something for. ⚠️ AND THE HONEST CONSTRAINT REMAINS: THE BOARD IS FULL AT 1,000,000 ACROSS 37 FUNDED NAMES. Funding CIEN means trimming something, and that decision belongs at the 10 DECEMBER REVIEW with TSEM and AGLT, not today.
A25: TSM | B25: Taiwan Semiconductor | C25: The world's chip factory — actually manufactures the chips Nvidia, Apple and AMD design. | D25: 1987 | E25: Taiwan | F25: 90,557 | G25: Makes, packages and tests chips for other companies, selling in Taiwan, China, Europe, the Middle East, Africa, Japan and the United States. | H25: To manufacture the chips its customers design, for computing, phones, cars, connected devices and home electronics. | I25: Foundry, Equipment & Test | J25: YES | K25: 147.5 | L25: 54856.42 | M25: 74000 | N25: 430.26 | O25: 2026-09-17 | P25: =COUNTIF('Full Log'!$A:$A,$A25) | Q25: 2026-07-21 | R25: 2026-09-19 | S25: 2. A small commission quirk. For your TSM row, POEMS included the $8.56 commission in the cost figure. For today's two orders it didn't — the cost is exactly shares × price. That's almost certainly because they haven't settled yet. So each of those two cost bases may creep up by $8.56 in a later snapshot. Nothing to fix; just don't be surprised by it.
A26: MU | B26: Micron Technology | C26: Memory chips, including the high-speed HBM memory that feeds AI processors. | D26: 1978 | E26: Idaho, United States | F26: 53,000 | G26: Four business units making memory and storage chips, with sales in the US, Taiwan, Japan, mainland China, Hong Kong and Europe. | H26: Aims to make the memory and storage chips used in data centres, phones, cars and computers. | I26: Memory & Storage | J26: YES | K26: 35.45 | L26: 22581.58 | M26: 51000 | N26: 977.5 | O26: 2026-09-17 | P26: =COUNTIF('Full Log'!$A:$A,$A26) | Q26: 2026-07-20 | R26: 2026-09-18 | S26: It is genuinely at the cheap end of its own range. Meta at $582.61 sits near the bottom of where it has traded all year ($520 low, $796 high). Compare that to Micron, SanDisk and Lumentum, which after this morning are all in the upper half of their yearly range. You are buying low on this one and high on those.
A27: SKHY | B27: SK hynix (NASDAQ ADR, listed Jul 10 '26) | C27: Korean memory maker — the leading supplier of HBM memory used by AI chips. | D27: 1983 | E27: South Korea | F27: 47,639 | G27: Korean maker of memory and storage chips selling across Korea, China, the rest of Asia, the United States and Europe; also makes chips to order. | H27: Aims to supply memory and storage chips for servers, phones, computers and cars. | I27: Memory & Storage | J27: YES | K27: 15 | L27: 1913.26 | N27: 182.99 | O27: 2026-09-17 | P27: =COUNTIF('Full Log'!$A:$A,$A27) | Q27: 2026-07-21 | R27: 2026-09-17 | S27: Which leaves the Jul 28 anomaly unexplained: that run reached ARM, AEHR, SKHY, CRWV, NBIS and 53 others, all of which are denied today. The most likely explanation is that FMP tightened the Basic sample list sometime between Jul 28 and Jul 30 and your job was quietly caught by it. I can't prove that from outside, and it doesn't change what you should do — but I'm not going to pretend I have a clean account of it.
A28: SNDK | B28: SanDisk | C28: Flash memory and SSD storage, spun out of Western Digital. | D28: 2024 | E28: California, United States | F28: 11,000 | G28: Makes flash-memory drives and cards, selling in the US, Europe, the Middle East, Africa and Asia to computer makers, data centres and retailers. | H28: Aims to supply fast flash storage for computers, phones, cars and data centres. | I28: Memory & Storage | N28: 1530.9 | O28: 2026-09-15 | P28: =COUNTIF('Full Log'!$A:$A,$A28) | Q28: 2026-07-22 | R28: 2026-09-13 | S28: You are lowering the cost of something you already own and believe in. Your 56 Meta shares cost you $664 each and are showing a loss of about 11%. Adding at $582 brings that average down. That is very different from Lumentum or SanDisk, where you would be starting a fresh bet at the top of a news spike.
A29: STX | B29: Seagate Technology | C29: Hard disk drives — the bulk storage that fills data centres. | D29: 1978 | E29: Singapore | F29: 30,000 | G29: Supplies storage drives and systems from Singapore, the United States and the Netherlands, selling to equipment makers, distributors and retailers. | H29: Aims to provide the drives and systems that store the world's growing pile of data. | I29: Memory & Storage | N29: 771.81 | O29: 2026-09-15 | P29: =COUNTIF('Full Log'!$A:$A,$A29) | Q29: 2026-07-29 | R29: 2026-09-13 | S29: I caught this because when I pulled the full history tables for those names, the number stored on the board matched the Jul 29 row exactly, every single time. ARM 224.89, SNDK 1015.89, STX 764.43, DELL 369.64, and thirty-plus more.
A30: AAOI | B30: Applied Optoelectronics | C30: Optical transceivers that carry data as light inside data centres. | D30: 1997 | E30: Texas, United States | F30: 4,691 | G30: Designs and makes fibre-optic networking parts, with operations in the United States, Taiwan and China. | H30: Aims to supply the light-based parts that move data inside data centres and across cable and phone networks. | I30: Networking & Optical | N30: 95.29 | O30: 2026-09-15 | P30: =COUNTIF('Full Log'!$A:$A,$A30) | Q30: 2026-07-22 | R30: 2026-09-16 | S30: Why it inflected. On July 29 AXT signed a supply agreement with Lumentum — that's LITE, already in this same group — running to end-2031. Lumentum pays $43.5M up front and another $43.5M in 2028, $87M total, applied as credits against reserved wafer capacity. That is a customer pre-paying for years of flour. The very next day AXT reported Q2 with adjusted earnings of $0.19 against $0.07 expected — nearly triple. Gross margin jumped from the low-30s to 44.9%.
A31: ALAB | B31: Astera Labs | C31: Connectivity chips that link AI processors together at very high speed. | D31: 2017 | E31: California, United States | F31: 756 | G31: Small chip designer operating in the United States and Taiwan, selling to very large data-centre operators and equipment makers. | H31: Aims to move data quickly between the parts inside cloud and artificial-intelligence computers. | I31: Networking & Optical | J31: YES | K31: 15 | L31: 3805.47 | M31: 11000 | N31: 293.56 | O31: 2026-09-17 | P31: =COUNTIF('Full Log'!$A:$A,$A31) | Q31: 2026-07-21 | R31: 2026-09-17 | S31: One last flag: APH and LITE sit in the same dashboard group. Adding aggressively to both concentrates dad further into the interconnect layer, which already includes ANET, CRDO and ALAB. That's a fine theme — it's just no longer a diversifying one.
A32: ANET | B32: Arista Networks | C32: High-speed network switches that connect the servers in AI data centres. | D32: 2004 | E32: California, United States | F32: 5,115 | G32: Sells computer-network equipment and software across the Americas, Europe, the Middle East, Africa and Asia-Pacific, direct and through resellers. | H32: Aims to supply the networking gear that connects data centres, offices and cloud services. | I32: Networking & Optical | J32: YES | K32: 98 | L32: 15585.57 | M32: 25000 | N32: 199.53 | O32: 2026-09-17 | P32: =COUNTIF('Full Log'!$A:$A,$A32) | Q32: 2026-07-24 | R32: 2026-09-13 | S32: One last flag: APH and LITE sit in the same dashboard group. Adding aggressively to both concentrates dad further into the interconnect layer, which already includes ANET, CRDO and ALAB. That's a fine theme — it's just no longer a diversifying one.
A33: APH | B33: Amphenol | C33: Connectors and cables — the physical plumbing of all electronics. | D33: 1932 | E33: Connecticut, United States | F33: 170,000 | G33: Three segments making electrical, electronic and fibre-optic connectors, cables and sensors in the United States, China and other countries. | H33: Aims to supply the connectors and cables that join electronic equipment in cars, planes, phones and data centres. | I33: Networking & Optical | J33: YES | K33: 32 | L33: 2004.4 | M33: 15000 | N33: 78.37 | O33: 2026-09-17 | P33: =COUNTIF('Full Log'!$A:$A,$A33) | Q33: 2026-07-22 | R33: 2026-09-15 | S33: One loose end: APH still shows 16 shares, so the $148.50 limit either wasn't placed or hasn't filled. It's at $150.31 now, so that limit is still realistic if dad wants it — but it now competes with META for the same dollars, and META at 17.75x is the better use of $2,000 than APH at 29.8x forward.
A34: AXTI | B34: AXT Inc | C34: Grows the crystal wafers (indium phosphide) that optical components are built on. | D34: 1986 | E34: California, United States | F34: 1,541 | G34: Makes the wafer discs chips are built on, selling directly in the US, China and Europe and via agents in Japan, Taiwan and Korea. | H34: Aims to supply specialty base materials used in lasers, sensors, wireless devices and solar cells. | I34: Networking & Optical | N34: 57.7 | O34: 2026-09-15 | P34: =COUNTIF('Full Log'!$A:$A,$A34) | Q34: 2026-08-06 | R34: 2026-09-15 | S34: AEHR is a judgement call worth being clear about. Aehr makes the ovens, in effect — machines that stress-test chips while they're still on the wafer, before anyone slices them up. Historically most of its revenue came from silicon carbide chips for electric vehicles, which is why it was sitting in Chips Manufacturing. The newer and faster-growing part of the business is testing silicon-photonics and AI optical devices, which is presumably why you want it next to LITE, COHR, AAOI and now AXTI.
A35: CIEN | B35: Ciena | C35: Ciena — the laser equipment that pushes huge amounts of data down fibre-optic cables. | D35: 1992 | E35: Maryland, United States | F35: 9,080 | G35: Serves more than 1,700 customers across the Americas, Europe and Asia-Pacific, backed by 4,500+ research staff and 2,400+ patents. | H35: Aims to build adaptive networks that keep pace with exploding bandwidth demand and help customers thrive in the AI era. | I35: Networking & Optical | N35: 334.33 | O35: 2026-09-15 | P35: =COUNTIF('Full Log'!$A:$A,$A35) | Q35: 2026-08-10 | R35: 2026-09-14 | S35: (5) DECISION: NO BUDGET CHANGES, NOTHING BOUGHT OR SOLD, GROUP 4 STAYS AT 83,000. CIEN IS TRACKED, NOT FUNDED. Conviction HIGH. ⚠️ WHAT WOULD CHANGE MY MIND ON CIEN: two consecutive quarters of revenue growth above 25% WITH GAAP operating margin holding above 15% - that would make it the only profitable pure optical-systems company on the board and worth displacing something for. ⚠️ AND THE HONEST CONSTRAINT REMAINS: THE BOARD IS FULL AT 1,000,000 ACROSS 37 FUNDED NAMES. Funding CIEN means trimming something, and that decision belongs at the 10 DECEMBER REVIEW with TSEM and AGLT, not today.
A36: COHR | B36: Coherent | C36: Lasers and optical components for data centres and industrial use. | D36: 1971 | E36: Pennsylvania, United States | F36: 30,216 | G36: Three segments - networking, materials and lasers - making optical parts and laser systems for industry, communications and electronics worldwide. | H36: Aims to supply the light-based parts and laser machines used in factories, data centres and research. | I36: Networking & Optical | N36: 271.17 | O36: 2026-09-15 | P36: =COUNTIF('Full Log'!$A:$A,$A36) | Q36: 2026-08-05 | R36: 2026-09-16 | S36: So the label now describes where the growth is coming from, not where the money currently comes from. That's a defensible way to organise a watchlist — but keep in mind when you look at that group that AEHR's EV exposure hasn't disappeared, and the EV chip cycle has been weak. If silicon carbide demand stays soft, AEHR can go down while the rest of the photonics shelf goes up. It won't move in sympathy with its new neighbours the way LITE and COHR move with each other.
A37: CRDO | B37: Credo Technology | C37: High-speed cables and chips that move data inside AI server racks. | D37: 2008 | E37: Cayman Islands | F37: 807 | G37: Sells high-speed cables, optical modules and chips in the United States, Taiwan, mainland China and Hong Kong, and licenses its designs. | H37: Aims to move data quickly and reliably between machines in data centres. | I37: Networking & Optical | J37: YES | K37: 54 | L37: 7700.99 | M37: 18000 | N37: 168.25 | O37: 2026-09-17 | P37: =COUNTIF('Full Log'!$A:$A,$A37) | Q37: 2026-07-21 | R37: 2026-09-15 | S37: One last flag: APH and LITE sit in the same dashboard group. Adding aggressively to both concentrates dad further into the interconnect layer, which already includes ANET, CRDO and ALAB. That's a fine theme — it's just no longer a diversifying one.
A38: FN | B38: Fabrinet | C38: Contract manufacturer that builds optical modules for other companies. | D38: 1999 | E38: Cayman Islands | F38: 16,457 | G38: Contract manufacturer serving North America, Asia-Pacific and Europe, assembling optical and precision electronic products for other brands. | H38: Aims to build complex optical and electronic products for the companies that design them. | I38: Networking & Optical | N38: 380.92 | O38: 2026-09-17 | P38: =COUNTIF('Full Log'!$A:$A,$A38) | Q38: 2026-07-21 | R38: 2026-09-18 | S38: Portfolio now: $560,432 cost, $683,857 market value, +$123,426 (+22.02%). A strong day across the board — 109 of 112 names repriced, and the tone was risk-on: PLTR +29%, AAOI +19%, ARM +17%, FN +16%, your own AMD +7% and AVGO +6.6%.
A39: GLW | B39: Corning | C39: Corning — optical fibre for networks and the tough glass on phone screens. | D39: 1851 | E39: New York, United States | F39: 67,200 | G39: Five businesses - optical cable, display glass, specialty materials, car parts and lab products - operating across the US, Asia and Europe. | H39: Aims to use its glass and ceramics know-how to serve communications, screens, cars and laboratories. | I39: Networking & Optical | N39: 143.57 | O39: 2026-09-15 | P39: =COUNTIF('Full Log'!$A:$A,$A39) | Q39: 2026-07-21 | R39: 2026-09-15 | S39: $119.26, no budget/position, blank as requested. Fair warning on what the card will show you: this is a wild one — opened the year at $36.35 (+228% YTD even now), ran to a $233.67 high in May, and has since been cut in half. Street says $57.50 / $151.30 / $220 across 6 analysts (avg = +27% conviction). Revenue +51% YoY on the datacenter optics ramp, but it's burning cash hard — FCF −$449M against $507M of TTM revenue as it builds capacity, so no PE, and Rule of 40 is deeply negative on the FCF basis. It behaves more like a call option on 800G/1.6T transceiver share gains than like GLW or FN.
A40: LITE | B40: Lumentum | C40: Lasers and optical modules; a key supplier for AI data-centre networking. | D40: 2015 | E40: California, United States | F40: 10,562 | G40: Two segments, cloud and networking parts plus industrial lasers, selling across the Americas, Asia-Pacific, Europe, the Middle East and Africa. | H40: Aims to supply the light-based parts and lasers used in data centres, networks and factories. | I40: Networking & Optical | J40: YES | K40: 11.5 | L40: 9372.74 | M40: 14000 | N40: 893.61 | O40: 2026-09-17 | P40: =COUNTIF('Full Log'!$A:$A,$A40) | Q40: 2026-07-22 | R40: 2026-09-17 | S40: So the label now describes where the growth is coming from, not where the money currently comes from. That's a defensible way to organise a watchlist — but keep in mind when you look at that group that AEHR's EV exposure hasn't disappeared, and the EV chip cycle has been weak. If silicon carbide demand stays soft, AEHR can go down while the rest of the photonics shelf goes up. It won't move in sympathy with its new neighbours the way LITE and COHR move with each other.
A41: CRM | B41: Salesforce | C41: Salesforce — the customer-management software used by sales teams worldwide. | D41: 1999 | E41: California, United States | F41: 83,334 | G41: Sells customer-management software in the United States, Europe and Asia-Pacific to banks, hospitals, manufacturers, carmakers and government bodies. | H41: To connect companies with their customers through software, increasingly using automated assistants that work alongside staff. | I41: AI Software, Security & Infrastructure | N41: 255.65 | O41: 2026-09-15 | P41: =COUNTIF('Full Log'!$A:$A,$A41) | Q41: 2026-07-21 | R41: 2026-09-17 | S41: Nothing on either list reports earnings between today and Aug 20. The nearest is Salesforce on Aug 26 (company-confirmed). Twenty days out — far enough that you're not gambling on an earnings print, but close enough that you should know it's coming.
A42: CRWD | B42: CrowdStrike | C42: CrowdStrike — cloud security that protects company laptops and servers. | D42: 2011 | E42: Texas, United States | F42: 10,698 | G42: Sells computer security by subscription over the internet in the United States and internationally, protecting company devices, cloud systems and data. | H42: To protect an organisation's devices, cloud systems, staff identities and data through one subscription platform. | I42: AI Software, Security & Infrastructure | J42: YES | K42: 40 | L42: 3914.12 | N42: 245.7 | O42: 2026-09-17 | P42: =COUNTIF('Full Log'!$A:$A,$A42) | Q42: 2026-07-20 | R42: 2026-09-17 | S42: How cost and market value both show up. The reference poster only shows one number per company. Yours shows two, like this: the *width* of each slice is how much of the portfolio that stock is worth today, and the coloured band on the outside rim is your profit or loss on it. Gold band = profit, red band = loss, and the deeper the band, the bigger the move. Think of each slice as a glass of water: the whole glass is what it's worth now, and the coloured layer at the top is the part that's pure gain (or, in red, how far underwater you are). AMAT and CRWD have fat gold rims because they've roughly doubled; META, TSLA and IBM show red.
A43: CRWV | B43: CoreWeave | C43: CoreWeave — rents Nvidia GPU computing power to AI companies. | D43: 2017 | E43: New Jersey, United States | F43: 2,189 | G43: Rents computing power over the internet in the United States, supplying specialist chips, storage and networking used for artificial-intelligence work. | H43: Aims to run complex artificial-intelligence computing at large scale through its own cloud software and services. | I43: AI Software, Security & Infrastructure | N43: 80.92 | O43: 2026-09-15 | P43: =COUNTIF('Full Log'!$A:$A,$A43) | Q43: 2026-07-20 | R43: 2026-09-19 | S43: CORZ was overdue. When I added Core Scientific on Wednesday I flagged at the time that Neocloud Watch was the better home and Fintech was a poor fit. It's a bitcoin miner converting its power-heavy sites into AI computing rental — that is the neocloud story exactly, same as IREN, CIFR and HUT sitting beside it now. Its planned merger with CoreWeave was called off, so it's back to standing on its own. The group now reads consistently.
A44: DDOG | B44: Datadog | C44: Monitoring software that tells companies the moment their systems break. | D44: 2010 | E44: New York, United States | F44: 8,100 | G44: Runs an internet-based service that watches over customers' software and computer systems, sold in the United States and internationally. | H44: To let organisations see how their software and computer systems are performing and keep them secure. | I44: AI Software, Security & Infrastructure | N44: 230.27 | O44: 2026-09-15 | P44: =COUNTIF('Full Log'!$A:$A,$A44) | Q44: 2026-07-28 | R44: 2026-08-06 | S44: That's the problem. Growth compared to a year ago still looks great at 36%. But the quarter-to-quarter momentum has essentially stopped. Investors paying a very high price for a fast-growing company get nervous when the speed drops that sharply, even if the absolute numbers beat expectations. There's also a report from Aug 3 that OpenAI's usage of Datadog fell 10–20% versus the prior quarter — big AI customers are a meaningful chunk of the recent growth.
A45: DELL | B45: Dell Technologies | C45: Servers and PCs; one of the largest suppliers of AI server systems. | D45: 1984 | E45: Texas, United States | F45: 97,000 | G45: Designs, makes and sells computers and data-centre equipment across the Americas, Europe, the Middle East and Asia, split between business infrastructure and personal computers. | H45: Aims to supply computing products, services and financing to businesses, governments, schools, hospitals and consumers worldwide. | I45: AI Software, Security & Infrastructure | N45: 543.51 | O45: 2026-09-15 | P45: =COUNTIF('Full Log'!$A:$A,$A45) | Q45: 2026-07-21 | R45: 2026-09-16 | S45: It moved in commit `1228826` (the same push as the AEHR move), and the AEHR revert afterwards only touched AEHR. Checking the live file just now: Neocloud Watch contains DELL, HPE, SMCI, IREN, NBIS, CRWV, APLD, CIFR, HUT, NOK and CORZ — 11 names. Fintech / Digital Platform is down to 14 and no longer lists it.
A46: FTNT | B46: Fortinet | C46: Fortinet — firewalls and network security hardware and software. | D46: 2000 | E46: California, United States | F46: 15,109 | G46: Sells computer security and networking products worldwide, including firewalls, its own security chips, and cloud-based protection services. | H46: To bring computer networking and security together into one connected system for customers worldwide. | I46: AI Software, Security & Infrastructure | N46: 172.37 | O46: 2026-09-15 | P46: =COUNTIF('Full Log'!$A:$A,$A46) | Q46: 2026-07-25 | R46: 2026-09-18 | S46: One honest note on Fortinet, since Dad has it on the list at under $100: it reported a strong quarter on July 29 — revenue $2.05B up 26%, billings up 33%, earnings up 41%, and it raised full-year guidance. That's why it's near its 52-week high at $168 rather than anywhere near $100. Dad's number on that one looks anchored to a price from a long time ago.
A47: IBM | B47: IBM | C47: Enterprise software and consulting, plus one of the leading quantum computing programmes. | D47: 1911 | E47: New York, United States | F47: 264,300 | G47: Four segments - software, consulting, computing equipment and customer financing - with customers across the Americas, Europe, Africa, the Middle East and Asia. | H47: To provide combined computing products and services, centred on cloud computing and artificial intelligence, to large organisations. | I47: AI Software, Security & Infrastructure | N47: 248.37 | O47: 2026-09-15 | P47: =COUNTIF('Full Log'!$A:$A,$A47) | Q47: 2026-07-21 | R47: 2026-09-15 | S47: Dad's second note is done and live. APP (AppLovin) is now in the SaaS group and IBM has moved from SaaS to Quantum, sitting next to IONQ. The dashboard is at 111 tickers across 17 groups, all checks green (no broken numbers, no errors, search finds "APP"), committed and pushed. Refresh the page and you'll see it.
A48: IONQ | B48: IonQ | C48: Builds quantum computers using trapped ions; still early-stage and loss-making. | D48: 2015 | E48: Maryland, United States | F48: 1,132 | G48: Builds quantum computers in the United States and Switzerland and sells access to them directly and through the Amazon, Microsoft and Google cloud services. | H48: To develop quantum computers, plus quantum-based secure communications and detection systems, and sell access to and support for them. | I48: AI Software, Security & Infrastructure | N48: 37.05 | O48: 2026-09-15 | P48: =COUNTIF('Full Log'!$A:$A,$A48) | Q48: 2026-07-20 | R48: 2026-09-17 | S48: Dad's second note is done and live. APP (AppLovin) is now in the SaaS group and IBM has moved from SaaS to Quantum, sitting next to IONQ. The dashboard is at 111 tickers across 17 groups, all checks green (no broken numbers, no errors, search finds "APP"), committed and pushed. Refresh the page and you'll see it.
A49: IREN | B49: IREN (Iris Energy) | C49: Data-centre operator shifting from bitcoin mining to AI computing. | D49: 2018 | E49: New South Wales, Australia | F49: 257 | G49: Owns and runs data centres, electrical infrastructure and computing hardware in Australia and Canada, and mines bitcoin. | H49: Aims to own the whole chain behind its business, from electricity supply and buildings to the computers themselves. | I49: AI Software, Security & Infrastructure | N49: 41.58 | O49: 2026-09-15 | P49: =COUNTIF('Full Log'!$A:$A,$A49) | Q49: 2026-07-21 | R49: 2026-09-19 | S49: It moved in commit `1228826` (the same push as the AEHR move), and the AEHR revert afterwards only touched AEHR. Checking the live file just now: Neocloud Watch contains DELL, HPE, SMCI, IREN, NBIS, CRWV, APLD, CIFR, HUT, NOK and CORZ — 11 names. Fintech / Digital Platform is down to 14 and no longer lists it.
A50: NBIS | B50: Nebius Group | C50: Nebius — European AI cloud provider spun out of Yandex. | D50: 2000 | E50: Netherlands | F50: 1,543 | G50: Builds and rents large banks of computers for artificial intelligence work in the US, UK and elsewhere; also owns a retraining school and a self-driving vehicle unit. | H50: To build the full stack of computing infrastructure that the world's artificial intelligence industry needs. | I50: AI Software, Security & Infrastructure | N50: 207.37 | O50: 2026-09-15 | P50: =COUNTIF('Full Log'!$A:$A,$A50) | Q50: 2026-07-21 | R50: 2026-09-19 | S50: Which leaves the Jul 28 anomaly unexplained: that run reached ARM, AEHR, SKHY, CRWV, NBIS and 53 others, all of which are denied today. The most likely explanation is that FMP tightened the Basic sample list sometime between Jul 28 and Jul 30 and your job was quietly caught by it. I can't prove that from outside, and it doesn't change what you should do — but I'm not going to pretend I have a clean account of it.
A51: NET | B51: Cloudflare | C51: Cloudflare — speeds up and protects a large share of the world's websites. | D51: 2009 | E51: California, United States | F51: 5,156 | G51: Runs a worldwide network that protects and speeds up business websites, plus tools for software builders and free services for the public. | H51: To give businesses everywhere cloud-based security, faster websites, and building blocks for their own software. | I51: AI Software, Security & Infrastructure | N51: 327.23 | O51: 2026-09-15 | P51: =COUNTIF('Full Log'!$A:$A,$A51) | Q51: 2026-07-25 | R51: 2026-08-05 | S51: NET was a move, not an addition. Each stock can only sit in one group on the dashboard, so putting Cloudflare into SaaS took it out of Cybersecurity. Cybersecurity now has four names instead of five. If you'd rather it stayed in Cybersecurity, say the word and I'll put it back.
A52: NOW | B52: ServiceNow | C52: ServiceNow — workflow software that automates company IT and HR tasks. | D52: 2004 | E52: California, United States | F52: 29,187 | G52: Sells through resellers and partners in North America, Brazil, Europe, Africa, the Middle East and Asia-Pacific to government, banks, hospitals and manufacturers. | H52: To provide internet-based software that organises and automates the everyday work flowing between a company's departments. | I52: AI Software, Security & Infrastructure | N52: 141.9 | O52: 2026-09-15 | P52: =COUNTIF('Full Log'!$A:$A,$A52) | Q52: 2026-07-30 | R52: 2026-08-06 | S52: ⚠️ CRM, NOW and ADBE all traded down in Wednesday's extended hours — Salesforce −5.03%, ServiceNow −3.60%, Adobe −2.15% — and my researcher could not find any news to explain it. My own reading, and I want to label this clearly as my inference and not a sourced fact, is that these fell in sympathy with AppLovin, because APP's miss was specifically about AI underperforming and traders sold the whole AI-software basket. If I'm right and Salesforce opens around 5% lower, that's a *better* entry for you, not a worse one. But thin after-hours prints on stocks that didn't report are unreliable. Check the actual price at the open before you commit.
A53: ORCL | B53: Oracle | C53: Databases and business software, and now a large AI cloud provider. | D53: 1977 | E53: Texas, United States | F53: 141,000 | G53: Sells worldwide, directly and through partners, to businesses, government agencies and schools, supplying computing equipment alongside its software. | H53: To supply the databases, business software and rented computing power that organisations use to run their operations. | I53: AI Software, Security & Infrastructure | J53: YES | K53: 75 | L53: 12228.43 | M53: 13000 | N53: 147.61 | O53: 2026-09-18 | P53: =COUNTIF('Full Log'!$A:$A,$A53) | Q53: 2026-07-20 | R53: 2026-09-19 | S53: That matters because ORCL is your worst performer in dollar terms right now (−$1,042, −12.5%), and a budget that quietly got overrun is exactly how a losing position turns into a big losing position. I'm not saying sell it — just that the $1,686 line should be treated as a real ceiling this time, not a suggestion.
A54: PANW | B54: Palo Alto Networks | C54: Palo Alto Networks — the largest pure-play cybersecurity company. | D54: 2005 | E54: California, United States | F54: 16,068 | G54: Sells computer security products to companies, telecoms firms and governments across the Americas, Europe, the Middle East, Africa, Asia Pacific and Japan. | H54: To protect customers' networks, cloud systems, security teams and their new artificial intelligence systems. | I54: AI Software, Security & Infrastructure | J54: YES | K54: 38 | L54: 9491.14 | M54: 11000 | N54: 375.46 | O54: 2026-09-17 | P54: =COUNTIF('Full Log'!$A:$A,$A54) | Q54: 2026-07-21 | R54: 2026-09-19 | S54: The group tells a clean story now that it's isolated: FTNT and PANW are the profitable, cash-generating incumbents; CRWD and ZS are the scaled-but-barely-profitable platform players; NET is the expensive hyper-growth bet. Having them side by side makes the valuation spread obvious — you're paying 32× forward for Zscaler and 200× for Cloudflare for similar ~25-34% growth, which is exactly the kind of relative-value comparison the grouping should surface.
A55: PLTR | B55: Palantir | C55: Software that helps governments and companies make sense of huge amounts of data. | D55: 2003 | E55: Florida, United States | F55: 4,429 | G55: Sells software platforms in the United States, the United Kingdom and internationally, serving intelligence and defence agencies as well as businesses. | H55: To build software that helps governments and companies make sense of large amounts of data, including through artificial intelligence. | I55: AI Software, Security & Infrastructure | J55: YES | K55: 40 | L55: 5533.09 | M55: 16000 | N55: 176.24 | O55: 2026-09-17 | P55: =COUNTIF('Full Log'!$A:$A,$A55) | Q55: 2026-07-20 | R55: 2026-09-17 | S55: Portfolio now: $560,432 cost, $683,857 market value, +$123,426 (+22.02%). A strong day across the board — 109 of 112 names repriced, and the tone was risk-on: PLTR +29%, AAOI +19%, ARM +17%, FN +16%, your own AMD +7% and AVGO +6.6%.
A56: SNOW | B56: Snowflake | C56: Cloud data warehouse where companies store and analyse all their data. | D56: 2012 | E56: California, United States | F56: 9,060 | G56: Sells its internet-based data platform to organisations of many kinds in the United States and internationally. | H56: To let organisations gather all their data in one place to gain business insight, share it, and apply artificial intelligence to it. | I56: AI Software, Security & Infrastructure | N56: 322.98 | O56: 2026-09-15 | P56: =COUNTIF('Full Log'!$A:$A,$A56) | Q56: 2026-07-28 | R56: 2026-09-07 | S56: Three are genuine all-time-vs-52-week confusions, not staleness: ADBE 688.37 is the close of 19 Nov 2021, SNOW 401.89 the close of 16 Nov 2021, and NOW 234.08 is the split-adjusted all-time close of 28 Jan 2025 (1,170.39 ÷ 5, after ServiceNow's 5-for-1 split effective 17–18 Dec 2025). The rest are just stale.
A57: AEP | B57: American Electric Power | I57: Power & Electrification | N57: 120.61 | O57: 2026-09-15 | P57: =COUNTIF('Full Log'!$A:$A,$A57) | Q57: 2026-08-29 | R57: 2026-09-08 | S57: Sep 8, 2026: ISRG budget raised 20,000 -> 25,000 at Salee's instruction, funded by withdrawing AEP's 5,000 - AEP had zero shares and zero cost, so nothing was unwound. AEP was the one funded name failing the same under-15% growth test that cut 15 watchlist names on Sep 7: revenue growth 10.3%, Rule of 40 score -15.6.
A58: BE | B58: Bloom Energy | C58: Bloom Energy — fuel cells that generate on-site electricity for data centres. | D58: 2001 | E58: California, United States | F58: 2,214 | G58: Designs and builds fuel-cell units that turn natural gas, biogas or hydrogen into on-site electricity for data centres, utilities, hospitals, schools, shops and factories. | H58: To supply clean, reliable electricity generated right where it is used, without burning the fuel. | I58: Power & Electrification | N58: 259.35 | O58: 2026-09-15 | P58: =COUNTIF('Full Log'!$A:$A,$A58) | S58: No comment on record yet.
A59: BWXT | B59: BWX Technologies | C59: Builds the nuclear reactors that power US Navy submarines and carriers. | D59: 1867 | E59: Virginia, United States | F59: 10,400 | G59: Makes nuclear components and fuel, including precision parts for naval reactors, plus medical radioisotopes, steam generators and engineering services. | H59: To supply nuclear parts, fuel and services to government and commercial customers and support power plants through their life. | I59: Power & Electrification | N59: 146.7 | O59: 2026-09-15 | P59: =COUNTIF('Full Log'!$A:$A,$A59) | Q59: 2026-08-04 | R59: 2026-09-11 | S59: One housekeeping flag on my own sources: CNN's quote pages gave me clearly wrong numbers this morning (Centrus at $331 versus the correct $184.76, BWXT at $205 versus $173.79). I discarded them and used stockanalysis.com, cross-checked against Google Finance and dated news reports. I mention it only so you know I checked rather than trusted.
A60: CAT | B60: Caterpillar | C60: Caterpillar — the world's biggest maker of construction and mining machinery. | D60: 1925 | E60: Texas, United States | F60: 118,000 | G60: Makes diggers, loaders, mining trucks, engines, turbines and locomotives sold worldwide, and also lends customers the money to buy them. | H60: To supply the machines and engines used to build, mine and move things around the world. | I60: Power & Electrification | N60: 783.54 | O60: 2026-09-15 | P60: =COUNTIF('Full Log'!$A:$A,$A60) | Q60: 2026-08-08 | R60: 2026-09-07 | S60: PROMOTED TIER 5 TO TIER 4 (+20,000, 5,000 each): APP, FSLR, SE and CAT, each 5,000 to 10,000. Chosen from the twenty names sitting at exactly 5,000. ⚠️ ALAB was the obvious candidate on growth - revenue +98.5%, EPS +197% - but it carries 7,000, not 5,000, so promoting it would have cost only 3,000 and left 2,000 stranded, breaking the arithmetic. It stays at 7,000. IONQ topped the raw screen and was REJECTED: its 174.9% net margin is a non-operating-gain artifact already flagged on this board, not a real margin.
A61: CEG | B61: Constellation Energy | C61: America's largest nuclear power operator, selling electricity to data centres. | D61: 1999 | E61: Maryland, United States | F61: 15,339 | G61: Runs about 31,676 megawatts of nuclear, wind, solar, natural gas and hydro power plants across the Mid-Atlantic, Midwest, New York and Texas. | H61: To produce and sell electricity, natural gas and cleaner energy services to homes, businesses and public bodies in the United States. | I61: Power & Electrification | J61: YES | K61: 37 | L61: 9869.13 | M61: 17000 | N61: 262.8 | O61: 2026-09-17 | P61: =COUNTIF('Full Log'!$A:$A,$A61) | Q61: 2026-08-05 | R61: 2026-09-19 | S61: Three — two of your existing holdings report this week. Constellation (CEG) reports tomorrow, Aug 6, and Vistra (VST) reports Friday, Aug 7. You own both. Wait and see those before adding anything else to the power/energy side. CEG also declared a dividend of $0.4265 per share this morning.
A62: ETN | B62: Eaton | C62: Eaton — electrical equipment that manages power in buildings and data centres. | D62: 1916 | E62: Ireland | F62: 97,000 | G62: Makes electrical, aerospace, vehicle and hydraulic equipment through five divisions, selling in the US, Canada, Latin America, Europe and the Asia Pacific. | H62: To manage electrical and mechanical power for industrial, commercial and transport customers worldwide. | I62: Power & Electrification | J62: YES | K62: 19 | L62: 7879.55 | M62: 11000 | N62: 409.46 | O62: 2026-09-17 | P62: =COUNTIF('Full Log'!$A:$A,$A62) | Q62: 2026-07-22 | R62: 2026-09-18 | S62: The new group "Power and Electrification" now exists with all six names. Two of them are things you already own: ETN (19 shares, $7,879.55 cost) and GEV (2 shares, $2,147.30 cost). They moved out of Energy, so Energy shrinks from 13 names to 11 and the new group starts with real money in it rather than being an empty watchlist. Your total cost and market value are unchanged to the cent ($560,431.70 / $683,857.21) — nothing was bought or sold, the money just sits under a different heading now. PWR, POWL, NVT and HUBB are watchlist only.
A63: FPS | B63: Forgent Power Solutions | I63: Power & Electrification | N63: 31.36 | O63: 2026-09-15 | P63: =COUNTIF('Full Log'!$A:$A,$A63) | Q63: 2026-08-29 | R63: 2026-09-15 | S63: ⚠️⚠️ AND THE SCREEN FOUND A REAL DATA FAULT, WHICH IS THE BEST ARGUMENT FOR RUNNING IT: LUMENTUM (LITE) SHOWS A NET MARGIN OF MINUS 230.1% AND EPS OF MINUS 92.96. THAT CANNOT BE RIGHT AS A MARGIN. A company with a 72.1bn market cap, revenue growing 83.2%, a Rule of 40 of 87.0 and POSITIVE free cash flow of 0.11bn is not losing 2.3 times its revenue at the net line. It is most likely a genuine one-off non-cash charge - Lumentum has convertible notes and a convertible mark or an impairment produces exactly this shape - in which case the figure is TRUE but MEANINGLESS as a margin and must be labelled. Otherwise it is a vendor fault of the same kind already found on SKHY and FPS. ⚠️ WE HOLD 9,372.74 IN 11.5 SHARES AGAINST A 14,000 BUDGET, so 4,627.26 of room remains and it would be sized against a field we cannot trust. RESOLVE FROM THE 10-Q BEFORE ANY FURTHER LITE DEPLOYMENT. The standing ...
A64: FSLR | B64: First Solar | C64: The largest US solar-panel maker, and a winner from tariffs on foreign solar. | D64: 1999 | E64: Arizona, United States | F64: 7,900 | G64: Manufactures and sells solar panels and solar power solutions in the United States, France, India, Chile and other countries. | H64: To supply solar panels made with its own thin-film technology, rather than the usual silicon, to utilities and large power projects. | I64: Power & Electrification | J64: YES | K64: 10 | L64: 2003.56 | N64: 201.16 | O64: 2026-09-17 | P64: =COUNTIF('Full Log'!$A:$A,$A64) | Q64: 2026-08-08 | R64: 2026-09-17 | S64: ⚠️⚠️ CHECK NUMBER SIX: A POSITION HELD WITH NO APPROVED BUDGET. CrowdStrike appeared on the slide, I looked it up, and the board showed 40 SHARES AT $3,914.12 AGAINST A BUDGET OF NONE. THE SWEEP FOUND SEVEN MORE: CDNS $3,918.01 in 12 shares; CRWD $3,914.12 in 40 shares; CRM $3,749.91 in 21 shares; TER $3,567.37 in 10 shares; FSLR $2,003.56 in 10 shares; SKHY $1,913.26 in 15 shares; FN $1,604.56 in 3 shares; and INTC $1,127.56 in 25 shares. TOTAL $21,798.35 ACROSS EIGHT NAMES. THIS IS THE MIRROR IMAGE OF THE FAULT I HAVE CHASED ALL MONTH - I KEPT FINDING APPROVED MONEY WITH NO RULE; THIS IS SPENT MONEY WITH NO APPROVAL. A NAME WITH NO BUDGET HAS NO CEILING AND NO STOP. SKHY AND INTC HAVE DOCUMENTED REASONS; CDNS, CRWD, CRM, FSLR AND FN DO NOT, AND I WILL NOT INVENT ONE.
A65: GEV | B65: GE Vernova | C65: GE Vernova — gas and wind turbines plus electricity grid equipment. | D65: 2023 | E65: Massachusetts, United States | F65: 78,000 | G65: Three divisions: Power (gas, nuclear, hydro, steam), Wind (onshore and offshore turbines) and Electrification (grid gear, solar, storage), selling in the US, Europe, Asia and Africa. | H65: To supply the equipment and services that generate, move, convert and store electricity. | I65: Power & Electrification | J65: YES | K65: 10 | L65: 9603.86 | M65: 13000 | N65: 924.93 | O65: 2026-09-17 | P65: =COUNTIF('Full Log'!$A:$A,$A65) | Q65: 2026-07-31 | R65: 2026-09-19 | S65: I want to be fair to it, because it's the most interesting of the three rejects. AirJoule has a 50/50 joint venture with GE Vernova that is genuinely operating — they installed a unit at GE Vernova's research campus in New York on July 28. Kubota signed them as exclusive US residential partner on July 21 (the stock jumped 15% that day). They have $35M cash and no debt, funded into 2028. All five analysts covering it have targets above the current price — the lowest target, $6.00, sits above the $5.95 price.
A66: HUBB | B66: Hubbell | C66: Hubbell — electrical grid components and utility hardware. | D66: 1888 | E66: Connecticut, United States | F66: 18,000 | G66: Two divisions make power grid transmission and distribution components and communications gear, plus wiring devices, connectors and industrial controls, sold in the US and abroad. | H66: To make and sell the electrical parts that power grids, buildings and industry depend on. | I66: Power & Electrification | N66: 438.53 | O66: 2026-09-15 | P66: =COUNTIF('Full Log'!$A:$A,$A66) | Q66: 2026-08-03 | R66: 2026-09-16 | S66: The new group "Power and Electrification" now exists with all six names. Two of them are things you already own: ETN (19 shares, $7,879.55 cost) and GEV (2 shares, $2,147.30 cost). They moved out of Energy, so Energy shrinks from 13 names to 11 and the new group starts with real money in it rather than being an empty watchlist. Your total cost and market value are unchanged to the cent ($560,431.70 / $683,857.21) — nothing was bought or sold, the money just sits under a different heading now. PWR, POWL, NVT and HUBB are watchlist only.
A67: LEU | B67: Centrus Energy | C67: Centrus — the only US-owned uranium enricher, making HALEU fuel for new reactors. | D67: 1998 | E67: Maryland, United States | F67: 467 | G67: Supplies enriched uranium and other nuclear fuel components, and sells technical and manufacturing services, to customers in the US, Japan, the Netherlands and elsewhere. | H67: To supply the fuel that nuclear power plants run on, along with related technical and manufacturing work. | I67: Power & Electrification | N67: 142.12 | O67: 2026-09-15 | P67: =COUNTIF('Full Log'!$A:$A,$A67) | Q67: 2026-08-08 | R67: 2026-09-13 | S67: ⚠️ AND THE HONEST GAPS: LEU MINUS 17.91%, NBIS MINUS 7.93% AND ASTS MINUS 9.47% HAVE NO COMPANY-SPECIFIC SOURCED CAUSE. NO SOURCED CAUSE FOUND. For those three the macro is the only explanation available, and I am labelling that as inference rather than dressing it up. NBIS in fact fell 5.1% on 10 Sep DESPITE good news - a sovereign-AI partnership with Palantir and a Truist target of 355. For CRWV the only hard fact is RULE 10b5-1 INSIDER SALES ON 8 SEPTEMBER: CEO MICHAEL INTRATOR SOLD 307,692 SHARES AT ABOUT 100.08, ABOUT 30.8m, AND EVP CHEN GOLDBERG 22,424 AT 95.91. Pre-arranged plans reduce the signal, and the 'valuation skepticism' framing around it is a journalist's characterisation with no named analyst behind it - NOT a sourced cause.
A68: NEE | B68: NextEra Energy | C68: NextEra — the largest US utility and the world's biggest wind and solar operator. | D68: 1925 | E68: Florida, United States | F68: 17,300 | G68: Runs power plants using wind, sun, nuclear and natural gas plus power lines, batteries and pipelines; its Florida utility serves about 12 million people. | H68: To generate, store and deliver electricity across North America, leaning heavily on wind, sun and nuclear power. | I68: Power & Electrification | N68: 81.07 | O68: 2026-09-15 | P68: =COUNTIF('Full Log'!$A:$A,$A68) | Q68: 2026-07-25 | R68: 2026-08-29 | S68: > If you're deploying real capital into this group: CCJ or NEE for conviction, the five SMR/storage names only as small, sized-to-lose speculative positions. I'd resist the temptation to treat OKLO/SMR at −75%/−83% as "cheap" — down a lot isn't the same as cheap when there's no earnings floor underneath.
A69: OKLO | B69: Oklo | C69: Developing small fast reactors to power data centres; earned its first revenue in 2026. | D69: 2013 | E69: California, United States | F69: 215 | G69: Developing small nuclear plants called Aurora Powerhouse, each making 15 to 75 megawatts, plus technology to turn used nuclear fuel back into usable fuel. | H69: To supply electricity at large scale to US customers from its own small nuclear power plants. | I69: Power & Electrification | N69: 35.98 | O69: 2026-09-15 | P69: =COUNTIF('Full Log'!$A:$A,$A69) | Q69: 2026-07-21 | R69: 2026-09-18 | S69: The list appears to have shrunk between Jul 28 and Jul 30. Commit `de9db26` (the Jul 28 refresh) successfully updated 58 tickers including ARM, AEHR, SKHY, CRWV, NBIS, OKLO, SMCI, SNDK, WDC, MDB, NOW, NET, ZS, MELI, SE, NU — every one of which returns ACCESS DENIED now. Commit `680b95b` on Jul 30 got exactly the 23.
A70: PWR | B70: Quanta Services | C70: Quanta Services — builds and maintains electricity transmission lines. | D70: 1997 | E70: Texas, United States | F70: 69,500 | G70: Two divisions build and service electric power lines and substations, and underground gas, oil and industrial infrastructure, for utilities and energy companies. | H70: To build and maintain the infrastructure that delivers electricity, gas and communications. | I70: Power & Electrification | N70: 613.35 | O70: 2026-09-15 | P70: =COUNTIF('Full Log'!$A:$A,$A70) | Q70: 2026-08-05 | R70: 2026-09-15 | S70: The new group "Power and Electrification" now exists with all six names. Two of them are things you already own: ETN (19 shares, $7,879.55 cost) and GEV (2 shares, $2,147.30 cost). They moved out of Energy, so Energy shrinks from 13 names to 11 and the new group starts with real money in it rather than being an empty watchlist. Your total cost and market value are unchanged to the cent ($560,431.70 / $683,857.21) — nothing was bought or sold, the money just sits under a different heading now. PWR, POWL, NVT and HUBB are watchlist only.
A71: STRL | B71: Sterling Infrastructure | C71: Does the site groundwork and utilities underneath data centres and chip plants. | D71: 1955 | E71: Texas, United States | F71: 6,200 | G71: Prepares sites for data centres, warehouses and power plants, builds roads, bridges and airports, and pours house foundations across the southern and eastern United States. | H71: To provide site preparation, transport construction and building work in the United States through three business segments. | I71: Power & Electrification | N71: 459.02 | O71: 2026-09-15 | P71: =COUNTIF('Full Log'!$A:$A,$A71) | Q71: 2026-08-08 | R71: 2026-09-15 | S71: ⚠️⚠️ THAT LAST POINT IS THE SECOND LIMITATION FOUND IN OUR OWN SCREENS TODAY AND IT IS NOW WRITTEN DOWN AS A STANDING ROW: THE RULE OF 40 DOES NOT WORK ON CONTRACTORS. It was built for software, where free cash flow approximates structural profit. On a percentage-of-completion contractor it mostly measures customer prepayment timing - which is why FIX swung forty points in six months without the business changing. FOR FIX, EMCOR, IES, LIMBACH AND OUR OWN PWR AND STRL, USE OPERATING MARGIN AND BACKLOG CONVERSION INSTEAD: FIX's operating margin was 17.1% against 13.8% a year earlier, and 65-75% of backlog converts within twelve months.
A72: VRT | B72: Vertiv Holdings | C72: Vertiv — the power and cooling systems that keep data centres running. | D72: 2016 | E72: Ohio, United States | F72: 34,000 | G72: Makes the power and cooling equipment that keeps data centres and telephone networks running in more than 40 countries, under brands such as Liebert. | H72: To keep the equipment behind data centres and networks powered, cooled and running without interruption. | I72: Power & Electrification | J72: YES | K72: 40 | L72: 9838 | M72: 21000 | N72: 241.49 | O72: 2026-09-17 | P72: =COUNTIF('Full Log'!$A:$A,$A72) | Q72: 2026-07-21 | R72: 2026-09-19 | S72: Strategically it is also the cleanest fit for what you already own. APH is the interconnect layer — every AI rack you have exposure to through NVDA, AVGO, VRT, ANET and CRDO needs Amphenol's connectors and cable assemblies. It is the pick-and-shovel play on your own book, and it is your smallest deployed position relative to budget.
A73: VST | B73: Vistra | C73: Vistra — Texas power producer with nuclear and gas plants serving AI demand. | D73: 1882 | E73: Texas, United States | F73: 6,390 | G73: Serves about 5 million electricity and gas customers and runs roughly 44,000 megawatts of gas, nuclear, coal, solar and battery generation across US states. | H73: To generate electricity and sell it, along with natural gas, directly to homes, businesses and industry across the United States. | I73: Power & Electrification | J73: YES | K73: 57 | L73: 8133.29 | M73: 15000 | N73: 143.56 | O73: 2026-09-17 | P73: =COUNTIF('Full Log'!$A:$A,$A73) | Q73: 2026-07-23 | R73: 2026-09-16 | S73: Three — two of your existing holdings report this week. Constellation (CEG) reports tomorrow, Aug 6, and Vistra (VST) reports Friday, Aug 7. You own both. Wait and see those before adding anything else to the power/energy side. CEG also declared a dividend of $0.4265 per share this morning.
A74: XE | B74: X-energy (IPO Apr 24 '26) | C74: X-energy — small modular reactor developer; listed on the market in April 2026. | D74: 2009 | E74: Maryland, United States | F74: 889 | G74: Designs nuclear reactors and makes their fuel; its Xe-100 unit produces 80 megawatts of electricity or 200 megawatts of heat, and it manufactures TRISO-X reactor fuel. | H74: To design and supply nuclear reactors together with the special fuel they run on. | I74: Power & Electrification | N74: 15.03 | O74: 2026-09-15 | P74: =COUNTIF('Full Log'!$A:$A,$A74) | Q74: 2026-08-05 | R74: 2026-09-13 | S74: Two stocks are still showing Monday's price: XE (X-Energy) and YUM. Every free source I tried served me either a stale snapshot or a mid-day price with no closing print. Rather than put a number on the dashboard I couldn't stand behind, I left both at their Aug 3 close and said so in the dashboard's own header. They're watchlist names, so nothing you own is affected.
A75: CGNX | B75: Cognex | C75: Machine-vision systems that let factory robots and machines 'see'. | D75: 1981 | E75: Massachusetts, United States | F75: 2,745 | G75: Sells camera-and-software systems that inspect goods on factory and warehouse lines, serving the United States, Europe and Greater China. | H75: To automate factory and shipping work by letting machines see, identify, inspect and measure items such as phone parts and parcels. | I75: Healthcare & Robotics | J75: YES | K75: 62 | L75: 4067.62 | M75: 12000 | N75: 60.85 | O75: 2026-09-17 | P75: =COUNTIF('Full Log'!$A:$A,$A75) | Q75: 2026-07-21 | R75: 2026-09-13 | S75: Excellent — the real grouping. I've transcribed your note (INTL→INTC, CONX→CGNX, ONDAS→ONDS, and IBM moving to Quantum — nice touch). Before I flag the gaps, let me rebuild:
A76: ISRG | B76: Intuitive Surgical | C76: Maker of the da Vinci surgical robot used in hospitals worldwide. | D76: 1995 | E76: California, United States | F76: 17,021 | G76: Makes robotic surgery systems and instruments, sold with training and support to hospitals in the United States and internationally. | H76: To widen access to surgery done through very small cuts, which is gentler on patients than traditional open operations. | I76: Healthcare & Robotics | J76: YES | K76: 38 | L76: 16381.68 | M76: 32000 | N76: 383.54 | O76: 2026-09-17 | P76: =COUNTIF('Full Log'!$A:$A,$A76) | Q76: 2026-07-20 | R76: 2026-09-16 | S76: In my last message I gave you live prices for all ten names. I only actually retrieved five of them. MPWR, TSM, ISRG, ASML and MU I did not look up — I filled those numbers in myself. They were close to right, which is the worst kind of wrong, because nothing about them looked off. I've now gone back and pulled all five properly. Four of the five were incorrect:
A77: TEM | B77: Tempus AI | C77: Tempus AI — applies AI to medical and genetic data to guide cancer treatment. | D77: 2015 | E77: Illinois, United States | F77: 3,800 | G77: Runs laboratories and a data service in the United States that test patients' genes for doctors, and works with drug makers such as AstraZeneca and Merck. | H77: Aims to link doctors directly to its own laboratory testing and large stores of patient data so treatment choices are better informed. | I77: Healthcare & Robotics | N77: 68.85 | O77: 2026-09-15 | P77: =COUNTIF('Full Log'!$A:$A,$A77) | Q77: 2026-07-25 | R77: 2026-08-12 | S77: Also pre-existing on the base, not introduced here: four watchlist names (EOSE, TEM, KO, V) now sit outside their own 52-week bands. Those are the same names in the never-merged V/KO/PYPL delta bucket whose prices I already flagged as suspect, so I left them rather than bake a bad price into a widened range.
A78: AAPL | B78: Apple | C78: iPhone, Mac and services — the world's biggest consumer technology company. | D78: 1977 | E78: California, United States | F78: 166,000 | G78: Sells phones, computers, tablets, watches and headphones worldwide, and runs online stores and paid services such as music, television and payments. | H78: To design, make and market its own devices and services for shoppers, small businesses, schools, companies and governments around the world. | I78: Digital Platforms & Fintech | J78: YES | K78: 46 | L78: 11437.61 | M78: 24000 | N78: 337 | O78: 2026-09-17 | P78: =COUNTIF('Full Log'!$A:$A,$A78) | Q78: 2026-07-20 | R78: 2026-09-17 | S78: META doesn't own the road its customers travel on. Apple and Google own the phones. In 2021 Apple changed one privacy setting and it cost META roughly $10 billion a year. That can happen again. Second, Reality Labs (the headset and metaverse division) lost $4.6 billion in a single quarter and has no moat whatsoever — it is a bet, funded by the ads business. Third, regulators in Europe and the US keep circling.
A79: APP | B79: AppLovin | C79: Advertising software that helps mobile apps and games find new users. | D79: 2012 | E79: California, United States | F79: 898 | G79: Two segments, advertising and apps, serving advertisers, mobile app publishers, small businesses and streaming TV companies in the US and abroad. | H79: To provide advertising tools driven by artificial intelligence that help businesses find and reach customers. | I79: Digital Platforms & Fintech | M79: 18000 | N79: 331.46 | O79: 2026-09-15 | P79: =COUNTIF('Full Log'!$A:$A,$A79) | Q79: 2026-08-03 | R79: 2026-08-06 | S79: ⚠️ CRM, NOW and ADBE all traded down in Wednesday's extended hours — Salesforce −5.03%, ServiceNow −3.60%, Adobe −2.15% — and my researcher could not find any news to explain it. My own reading, and I want to label this clearly as my inference and not a sourced fact, is that these fell in sympathy with AppLovin, because APP's miss was specifically about AI underperforming and traders sold the whole AI-software basket. If I'm right and Salesforce opens around 5% lower, that's a *better* entry for you, not a worse one. But thin after-hours prints on stocks that didn't report are unreliable. Check the actual price at the open before you commit.
A80: CRCL | B80: Circle Internet Group | I80: Digital Platforms & Fintech | N80: 86.3 | O80: 2026-09-15 | P80: =COUNTIF('Full Log'!$A:$A,$A80) | Q80: 2026-08-15 | R80: 2026-09-01 | S80: Sep 1, 2026 edit 2 - THREE NEW BUDGETS OPENED TO FILL TWO BLANK GROUPS, at user request ('do it for those 3 stocks on budget for $5,000 each'). FSLR, V and NU each set to 5,000; all three are watchlist-only, shares None, cost None, no position taken. ⚠️ NOTE THE USER'S OWN SIZING DECISION, RECORDED BECAUSE IT DIFFERS FROM THE ADVICE: the recommendation was FSLR 5,000, V 10,000 and NU 5,000 for 20,000 total, which would have consumed the entire remaining unallocated budget. Salee chose 5,000 each for 15,000, HALVING the Visa line and leaving 5,000 unallocated. That is a more conservative allocation than proposed and is his call, not a transcription error. WHY THESE THREE. (1) FSLR (First Solar, group 5 Solar & Storage) - the ONLY investable name in that group at this portfolio's size. It is one of just two profitable members (net income 1.75bn, 32.5% margin, 44.0% gross margin) against ...
A81: HOOD | B81: Robinhood Markets | C81: Robinhood — the commission-free app for trading shares and crypto. | D81: 2013 | E81: California, United States | F81: 2,900 | G81: Runs an online investing service in the United States for shares and funds, and also offers credit cards, cash accounts and crypto wallets. | H81: To let ordinary people invest easily in shares and funds, with free learning material alongside. | I81: Digital Platforms & Fintech | N81: 110.45 | O81: 2026-09-15 | P81: =COUNTIF('Full Log'!$A:$A,$A81) | Q81: 2026-07-23 | R81: 2026-09-01 | S81: The honest bear case: Robinhood trades at 16.5× its revenue against a historical average of 11.9×. If it simply drifts back to its own normal valuation, that's 30%+ downside with nothing else going wrong. And its earnings depend on retail investors trading actively — in a dull market, that dries up fast.
A82: NFLX | B82: Netflix | C82: Netflix — the world's largest video streaming service. | D82: 1997 | E82: California, United States | F82: 16,000 | G82: Streams series, films, games and live programmes in many languages to paying subscribers who watch on televisions, phones and set-top boxes around the world. | H82: To be a worldwide entertainment service offering a wide range of programmes people can watch whenever they choose. | I82: Digital Platforms & Fintech | N82: 77.9 | O82: 2026-09-15 | P82: =COUNTIF('Full Log'!$A:$A,$A82) | Q82: 2026-08-08 | R82: 2026-09-07 | S82: ⚠️ THE LIST'S PREMISE DOES NOT SURVIVE CONTACT WITH A GROWTH MANDATE. 'Number one in the sector' is a claim about category rank, not about price or growth. Four of its own entries are names this board rejected precisely for failing to grow. Note also the list is titled number-one but contains three explicit number-TWOs (AMD, MA and CVX) plus one it calls a 'rising star' (NBIS), and it splits categories until everyone wins: GOOGL is number one in Search while META is number one in Social; NFLX is number one in Streaming while DIS is number one in Media. Subdivide finely enough and every company is number one of something.
A83: SE | B83: Sea Limited | C83: Sea Limited — Shopee shopping, Garena games and Monee payments across South-East Asia. | D83: 2009 | E83: Singapore | F83: 102,700 | G83: Runs the Shopee shopping marketplace, the Garena games business and Monee financial services across Southeast Asia and Latin America. | H83: To bring shopping, games and financial services to people across Southeast Asia and other regions through one technology company. | I83: Digital Platforms & Fintech | M83: 13000 | N83: 102.65 | O83: 2026-09-15 | P83: =COUNTIF('Full Log'!$A:$A,$A83) | S83: No comment on record yet.
A84: SHOP | B84: Shopify | C84: Shopify — the software that lets anyone set up and run an online store. | D84: 2004 | E84: Ontario, Canada | F84: 7,600 | G84: Provides software that lets shopkeepers of any size sell online, in physical stores and on marketplaces, and handles their payments, shipping and till equipment. | H84: To give merchants of any size the tools to run a business and sell wherever their customers are. | I84: Digital Platforms & Fintech | N84: 129.86 | O84: 2026-09-15 | P84: =COUNTIF('Full Log'!$A:$A,$A84) | Q84: 2026-07-25 | R84: 2026-08-08 | S84: > The through-line: this group splits cleanly into two things you already own the framework for — V/MA/PYPL are your "quality + value" wheelhouse (toll-road economics, the exact income-and-value lens you use on Thai equity), while COIN/HOOD/AFRM/SHOP are momentum-and-story names where valuation still has a long way to fall if growth blinks. Don't let them sit in one mental bucket.
A85: V | B85: Visa | C85: Visa — the world's largest payment network, earning a small fee on card transactions. | D85: 1958 | E85: California, United States | F85: 34,100 | G85: Runs VisaNet, a network that approves and settles card payments in the United States and internationally for banks, shops and governments. | H85: To move money for consumers, sellers, banks and governments through its payment network and card brands. | I85: Digital Platforms & Fintech | J85: YES | K85: 13 | L85: 4813.99 | M85: 9000 | N85: 369.93 | O85: 2026-09-17 | P85: =COUNTIF('Full Log'!$A:$A,$A85) | Q85: 2026-07-25 | R85: 2026-07-25 | S85: All 13 sets are in — but I caught a data problem: the agents returned enterprise value in $B instead of the EV/EBITDA ratio for every name (e.g. Visa "680" = its ~$670B EV, not a 28× multiple). P/FCF and everything else checks out. Let me send the three agents back to fetch the correct EV/EBITDA multiples before I write anything.
A86: ZETA | B86: Zeta Global | C86: Marketing software that uses data and AI to target customers. | D86: 2007 | E86: New York, United States | F86: 3,300 | G86: Sells cloud-based marketing and customer-data software to large companies in the United States and other countries. | H86: Aims to help large companies find, grow and keep customers more cheaply and effectively than rival marketing tools. | I86: Digital Platforms & Fintech | N86: 31.04 | O86: 2026-09-15 | P86: =COUNTIF('Full Log'!$A:$A,$A86) | Q86: 2026-07-21 | R86: 2026-09-17 | S86: ⚠️ One correction worth knowing: you may see headlines saying "Zeta missed on earnings per share." They're wrong. Data vendors compared an *adjusted* estimate against the company's *GAAP* actual — an apples-to-oranges comparison. Zeta never published an adjusted number. Ignore those headlines.
A87: ASTS | B87: AST SpaceMobile | C87: Building satellites that connect directly to ordinary mobile phones from space. | D87: 2019 | E87: Texas, United States | F87: 1,126 | G87: Designs and develops its BlueBird satellites from a base in Midland, Texas, to carry a mobile phone network in space. | H87: To run a mobile network from satellites so ordinary smartphones get service in places with no coverage on the ground. | I87: Space & Defence | N87: 58.77 | O87: 2026-09-15 | P87: =COUNTIF('Full Log'!$A:$A,$A87) | Q87: 2026-07-21 | R87: 2026-09-17 | S87: ASTS — the quote page served me a snapshot from July 13, eighteen days old, with no warning that it was old. The history table was current, so I used that (59.02). This is the one name in all 60 that rests on a single source. Everything else has at least two.
A88: AVAV | B88: AeroVironment | C88: Military drones and loitering munitions for the US and allied forces. | D88: 1971 | E88: Virginia, United States | F88: 4,091 | G88: Makes small pilotless aircraft, one-way strike drones, and space and cyber equipment for government agencies and businesses in the US and abroad. | H88: To supply robotic aircraft and related defence technology that give military users useful information and precise firepower. | I88: Space & Defence | J88: YES | K88: 18 | L88: 3758.3 | M88: 11000 | N88: 163.38 | O88: 2026-09-17 | P88: =COUNTIF('Full Log'!$A:$A,$A88) | Q88: 2026-07-20 | R88: 2026-09-18 | S88: Clear split. Group 7 holds RKLB/ASTS/SPACEX (space) and PLTR/AVAV/ONDS/MDB (drone & defense). I'll make Space and Drone & Defense adjacent groups, plus add the cash card to the Portfolio page. Starting with the data reindex.
A89: GE | B89: GE Aerospace | C89: GE Aerospace — builds and services jet engines for airlines and the military. | D89: 1892 | E89: Ohio, United States | F89: 57,000 | G89: Designs, builds and services jet engines, propellers and aircraft systems for airlines and armed forces in North America, Europe, Asia and the Middle East. | H89: To keep aircraft flying by making and maintaining the engines that power passenger and military planes. | I89: Space & Defence | N89: 307.05 | O89: 2026-09-15 | P89: =COUNTIF('Full Log'!$A:$A,$A89) | Q89: 2026-08-08 | R89: 2026-09-18 | S89: 🎯 RECOMMENDATION - ONE THING, NOT FOUR: DO NOT ADD A DEFENCE NAME. FIX THE DEFENCE BUDGET WE ALREADY HAVE. For 10 December: (1) L3Harris gets a dated buy row or the $9,000 is withdrawn - FOURTH time raised. (2) Revisit the RKLB $15,000 versus LHX $9,000 split, backwards on every quality measure; if RKLB is a bet on a moat not yet built, its money needs a MILESTONE not a date. (3) Screen GE Aerospace, the best business in the group and never funded. (4) Only then consider a big prime.
A90: KTOS | B90: Kratos Defense & Security | I90: Space & Defence | N90: 47.62 | O90: 2026-09-15 | P90: =COUNTIF('Full Log'!$A:$A,$A90) | Q90: 2026-09-03 | R90: 2026-09-03 | S90: Sep 3, 2026 - LHX added to the board at Salee's instruction (typed 'LHK'; L3Harris Technologies, NYSE: LHX, is the intended name - there is no US-listed LHK). Group 8, Defense, Drones & Public Safety, joining AMPX, PLTR, AVAV, ONDS, AXON, RCAT, LMT, RTX, NOC, KTOS. Budget 5,000; no position opened. Board goes 181 -> 182 tickers.
A91: LHX | B91: L3Harris Technologies | I91: Space & Defence | M91: 9000 | N91: 249.66 | O91: 2026-09-15 | P91: =COUNTIF('Full Log'!$A:$A,$A91) | Q91: 2026-09-03 | R91: 2026-09-18 | S91: 🎯 RECOMMENDATION - ONE THING, NOT FOUR: DO NOT ADD A DEFENCE NAME. FIX THE DEFENCE BUDGET WE ALREADY HAVE. For 10 December: (1) L3Harris gets a dated buy row or the $9,000 is withdrawn - FOURTH time raised. (2) Revisit the RKLB $15,000 versus LHX $9,000 split, backwards on every quality measure; if RKLB is a bet on a moat not yet built, its money needs a MILESTONE not a date. (3) Screen GE Aerospace, the best business in the group and never funded. (4) Only then consider a big prime.
A92: LUNR | B92: Intuitive Machines | C92: Builds Moon landers plus satellites and space services for NASA and defence customers. | D92: 2013 | E92: Texas, United States | F92: 525 | G92: Builds Moon landers and provides delivery, data and support services from Houston, Texas, for NASA, defence bodies and commercial customers. | H92: To carry cargo and equipment to the Moon and supply the communications and support services a working lunar economy would need. | I92: Space & Defence | N92: 13.87 | O92: 2026-09-15 | P92: =COUNTIF('Full Log'!$A:$A,$A92) | Q92: 2026-07-24 | R92: 2026-09-05 | S92: LUNR is the cleaner speculative story of the two — a NASA-contracted lunar-lander company with +54% revenue growth and a huge analyst gap ($41 avg vs $13 now). It's still burning cash and down 72% from its high, but at least the top line is compounding. It slots naturally next to RKLB/ASTS/SPCX as another sized-to-lose space bet.
A93: ONDS | B93: Ondas Holdings | C93: Defence and security drones and counter-drone systems, plus private wireless networks. | D93: 2014 | E93: Florida, United States | F93: 495 | G93: Two arms, private wireless networks and drones, sold in the US and abroad to railways, utilities, oil and gas firms, public safety bodies and government. | H93: To provide secure private wireless communications and self-flying drones that gather data and defend against hostile drones. | I93: Space & Defence | N93: 7.24 | O93: 2026-09-15 | P93: =COUNTIF('Full Log'!$A:$A,$A93) | Q93: 2026-07-20 | R93: 2026-09-17 | S93: Second — ⚠️ one number in your screenshot is wrong. POEMS shows ONDS at $8.37. The verified Aug 3 close was $8.23 — I checked it two ways and got 8.22 mid-session and 8.23 at the close. I used the verified figure, which is why the dashboard shows $655,382 rather than the $655,410 on your screen. The $28 gap is entirely that one line. It's immaterial to your P&L, but I'm not putting a number on the board that I couldn't confirm, and it's worth knowing your broker's mark can drift on thin small-caps.
A94: RKLB | B94: Rocket Lab | C94: Small rockets and satellites — a leading commercial space launch company. | D94: 2006 | E94: California, United States | F94: 2,600 | G94: Provides rocket launches and builds spacecraft, serving customers in the United States, Canada, Japan and elsewhere through two business segments. | H94: To launch small and medium rockets and supply satellites and parts for commercial and government space missions. | I94: Space & Defence | J94: YES | K94: 23 | L94: 1942.58 | M94: 15000 | N94: 67.82 | O94: 2026-09-17 | P94: =COUNTIF('Full Log'!$A:$A,$A94) | Q94: 2026-07-23 | R94: 2026-09-18 | S94: The cleanest confirmation: total cost rose from 546,807.07 to 548,720.33, a delta of exactly $1,913.26 — the SKHY purchase and nothing else. 47/47 share counts and cost bases match. (Also settled: the broker screen shows CRM at 1,888.07 and RKLB at 1,942.58, which confirms those two "discrepancies" were my transcription errors, as I said.)
A95: SPCX | B95: SpaceX | C95: SpaceX — rockets, Starship, and the Starlink satellite internet network. | D95: 2002 | E95: Texas, United States | F95: 22,000 | G95: Launches reusable rockets, runs the Starlink satellite internet network, and operates an artificial intelligence arm; serves the US, Ireland, Canada and beyond. | H95: To provide low-cost access to space with reusable rockets, deliver internet from satellites, and build artificial intelligence services. | I95: Space & Defence | N95: 143.49 | O95: 2026-09-15 | P95: =COUNTIF('Full Log'!$A:$A,$A95) | Q95: 2026-07-21 | R95: 2026-09-17 | S95: > Conviction: High — but on *valuation and position discipline*, not on "NVDA always goes up." > > Horizon: Long (2+ years) — this fits the 2026–2030 doubling objective. > > What would change my mind: (1) Aug 26 earnings guiding below ~$91B or gross margin slipping under 73% — that would say the pricing power is cracking; (2) any sign the hyperscalers are cutting 2027 capex plans; (3) NVDA rising above ~$260 before earnings, which would put it at a forward multiple where the cheapness argument stops working; (4) SpaceX or another marquee customer publicly dual-sourcing to AMD or in-house silicon.

Sheet Comment Log
A1: Ticker | B1: Week | C1: View | D1: Executive summary (green = positive, red = negative / risk)
A2: AMZN | B2: 2026-07-20 (Jul 20-26, 2026) | C2: MIXED | D2: + Advisor's runner-up buy: +26.9% to a 65-analyst target, cheapest of five candidates at 3.6x sales and 29.6x forward earnings; suggested GTC limit ~$246-248. Added 8 shares at $244.00 on Jul 22; now 202 shares at $46,595 cost, leaving $3,405 of the $50K plan. - Jul 30 earnings is the key risk: AWS growth below ~17% or a capex guide-down would break the thesis; ideal entry seen as after the print. FCF-based scoring deliberately harsh on AMZN (13.9) - it punishes mid-investment companies, so the metric looks worse than the business.
A3: AMZN | B3: 2026-07-27 (Jul 27 - Aug 02, 2026) | C3: MIXED | D3: RED FLAG: Q2 EPS of $5.75 includes a $53.4B pre-tax paper gain on the Anthropic stake; dashboard stores underlying TTM EPS of 8.61 ex-gain so the P/E isn't distorted. + Stock jumped 15% overnight after earnings, blowing straight through the standing buy limit. Post-earnings fundamentals refreshed on the dashboard at the Jul 30 close.
A4: AMZN | B4: 2026-08-03 (Aug 03-09, 2026) | C4: MIXED | D4: - Advisor pushed back on adding: least upside of ten names (+14.8% to target), only 2.5% below its 52-week high, 29.6x forward, 23% above Dad's limit - META preferred. + Robotics case: operating margin 11.4% to 13.7%; robot ~$3k/yr vs human ~$34k; 100 robotic centres in 18 months, 40% faster; Morgan Stanley sees up to $4B annual savings. Bought 7 shares at $285.36 on Aug 4 ($2,006 with fees); now 209 shares at avg cost $232.54, worth $59,360, +22.1%; sleeve essentially full with $1,399 left. - Watch item: if operating margin stalls below 14% next quarter despite the robot rollout, the savings are one-off, not structural.
A5: AMZN | B5: 2026-08-31 (Aug 31 - Sep 06, 2026) | C5: NEGATIVE | D5: R&D SPENDING ACROSS THE MEGA-CAPS, saved to notes at Salee's request from an Oxford Club graphic (Sep 5, 2026). Amazon's line: technology and infrastructure of $108,521M for FY2025, ended Dec 31 2025, up 22.6% from $88,544M in FY2024. Verified independently against Amazon's FY2025 10-K and its Q4 2025 earnings release on SEC EDGAR - both print the same figure. RED FLAG: ⚠️ AMAZON'S $108.5B IS NOT A RESEARCH NUMBER and must not be set beside the other six. Amazon reports no 'research and development' line at all - the tag does not even exist in its SEC XBRL data. 'Technology and infrastructure' is a wider bucket that also carries the running costs of AWS infrastructure. Amazon topping this chart is an artifact of how the line is drawn, not evidence that it out-researches Alphabet by 78%. Anyone quoting this as an R&D league table has the wrong end of it. Corrected ranking, latest reported fiscal year, US$ millions: AMZN 108,521 (+22.6%, technology & infrastructure, NOT R&D) - GOOGL 61,087 (+23.8%) - META 57,372 (+30.8%) - MSFT 35,562 (+9.5%) - AAPL 34,550 (+10.1%) - NVDA 18,497 (+43.2%) - TSLA 6,411 (+41.2%). The six genuine R&D lines total $213.5B. Fiscal calendars are not aligned: NVIDIA's year ended Jan 25 2026, Microsoft's Jun 30 2026, Apple's Sep 27 2025, and Amazon/Alphabet/Meta/Tesla Dec 31 2025 - so this is not a like-for-like comparison of the same twelve months. RED FLAG: ⚠️ THE SOURCE GRAPHIC IS A FULL YEAR STALE ON MICROSOFT. It printed $32.5B, +10.1% - that is Microsoft's fiscal 2025, ended Jun 30 2025. Fiscal 2026 ended Jun 30 2026 and the 10-K was filed Jul 29 2026, before the graphic's own stated 'as of Aug 2026' cutoff, so the current number was available and was not used. The true figure is $35,562M, +9.5%. That also flips the ranking: Microsoft is 4th, ahead of Apple's $34,550M, not 5th behind it. Six of the seven figures matched the SEC filings to the dollar; only Microsoft did not. Reading the growth rather than the level: Nvidia +43.2% and Tesla +41.2% are the fastest, but from small bases. In absolute dollars Meta added the most real research spend (+$13.5B) and Alphabet next (+$11.8B). Amazon's +$20.0B is the largest increase of all seven, but it is mostly infrastructure build - the same capex story already sitting in the AWS thesis, not incremental research. No board fields were changed by this entry; it is reference information only. (new, not yet condensed) Sep 5, 2026 - R&D SPENDING RECORDED FOR THE SEVEN MEGA-CAPS at Salee's request, saved to the per-stock notes page. Latest reported fiscal year, US$ millions, every figure independently verified against SEC filings: AMZN 108,521 (+22.6%) - GOOGL 61,087 (+23.8%) - META 57,372 (+30.8%) - MSFT 35,562 ... (new, not yet condensed) ⚠️ AMZN's 108,521 is its 'technology and infrastructure' line, not research and development. Amazon reports no R&D line at all - the tag does not exist in its SEC XBRL data - and that bucket also carries the running costs of AWS infrastructure. Amazon leading this chart is an artifact of how the ... (new, not yet condensed) WHERE THE REAL LINK IS: token consumption. Agents running 40-minute autonomous tasks burn far more tokens than chat, at 2.5x the price. That feeds inference silicon, memory, interconnect and power over 12-24 months - it does not show up in a two-day price move. Most direct listed beneficiaries in ...
A6: AMZN | B6: 2026-09-07 (Sep 07-13, 2026) | C6: NEUTRAL | D6: (new, not yet condensed) TIER 3 CONVICTION (+30,000, 10,000 each): AVGO 40,000 to 50,000, ASML 30,000 to 40,000, MU 30,000 to 40,000. ⚠️ AVGO now sits at 50,000 and therefore MOVES FROM TIER 3 TO TIER 2, joining GOOGL, TSM, MSFT, AMZN and META. ⚠️ AND THE HONEST CAVEAT: these three already had 30,899.18 of budget they have ... (new, not yet condensed) Corrected trailing net income: GOOGL 244.1bn, NVDA 192.9bn, AMZN 135.3bn, MSFT 133.7bn, AAPL 128.9bn, BRK 85.8bn, META 68.1bn. NVDA's graphic figure of 120.07bn was 61% too low and seven months stale - one recent quarter alone (59.7bn) is half that whole 'year'. (new, not yet condensed) But the corrected ranking has its own trap: GOOGL's lead rests on a disclosed 77.1bn after-tax unrealised equity gain and AMZN's on 53.4bn of pre-tax other income from Anthropic. On operating earnings NVDA is the most profitable business in America. (new, not yet condensed) AMZN IS FULL AND STOPS HERE: 48,600 invested against a 48,000 target. The business is not the problem - Q2 2026 net sales +20% to 200.6bn, AWS +37% to 42.2bn at a 39.4% operating margin, consolidated operating income 27.5bn. The CASH is the problem: Amazon's own reconciliation reads 'Free cash flow ...
A7: AMZN | B7: 2026-09-14 (Sep 14-20, 2026) | C7: MIXED | D7: - ⚠️⚠️ THE FIRST TRUE BUDGET BREACH THIS BOARD HAS EVER HAD, FOUND 16 SEPTEMBER. AMAZON HAS 48,600.75 INVESTED ACROSS 209 SHARES AGAINST AN APPROVED BUDGET OF 48,000.00 - OVER BY 600.75, OR 1.25%. It is the ONLY name in ninety-four where money SPENT exceeds money APPROVED. || ⚠️ THIS IS A WORSE CLASS OF FAULT THAN THE THREE FOUND EARLIER TODAY. The MRVL 4,000, the GOOGL 2,000 and the Micron 11,000 were PROMISES that exceeded or lacked a budget - not yet spent, fixable with a keystroke. THIS ONE IS ALREADY SPENT; the shares are bought. || The size looks like commission plus the gap between a planned amount and an actual fill price on the last tranche, but NO SOURCED CAUSE FOUND and I will not record a guess as a cause. Amazon has NO remaining schedule rows, so the breach cannot widen. || ⚠️ I HAVE DELIBERATELY NOT FIXED IT. Raising the budget to 48,600.75 breaks the board's hardest constraint - that all budgets sum to exactly 1,000,000 - unless 600.75 is taken from another name, and quietly moving approved money to tidy a rounding error is how a budget stops meaning anything. TWO HONEST OPTIONS ON 10 DECEMBER: (A) raise Amazon and take 600.75 from an unspent budget elsewhere, or (B) WRITE A TOLERANCE RULE - 2% or 1,000, whichever is smaller - permitting commission and fill drift. I FAVOUR (B): the alternative is re-cutting budgets every time a fill comes in a few cents high. RED FLAG: ⚠️⚠️ THE DISCLOSURE ITEM THAT MATTERS MORE THAN ANY COMPUTE HEADLINE, AND IT IS IN AMAZON'S OWN FILING. THE Q2 2026 EARNINGS RELEASE STATES VERBATIM: 'Second quarter 2026 net income includes non-operating pre-tax other income of $53.4 billion, primarily from our investments in Anthropic.' AGAINST OPERATING INCOME OF 27.5 BILLION. ⚠️ THE MARK ON A PRIVATE COMPANY WAS ROUGHLY TWICE THE ENTIRE OPERATING PROFIT OF AMAZON. The 10-Q shows 8.0bn invested from Q3 2023 to Q4 2025, carried at about 74.2bn at 31 March 2026, with 39.5bn of unrealised gain sitting in AOCI. ⚠️⚠️ CONFLICT DISCLOSED: ANTHROPIC MAKES ME, AND I WILL NOT OFFER A VIEW ON WHETHER THAT VALUATION IS RIGHT. || WHAT I CAN SAY IS WHAT IT MEANS FOR READING THE ACCOUNTS: WHEN A MARK ON ONE PRIVATE HOLDING IS TWICE OPERATING PROFIT, THE HEADLINE EPS IS NOT TELLING YOU ABOUT THE RETAIL AND CLOUD BUSINESS. AWS segment sales grew 37% to 42.2bn - THAT is the number to judge Amazon on. Amazon also guides CY2026 capex to 220bn, raised from 200bn. RED FLAG: ⚠️ AMAZON'S Q2 2026 NET INCOME OF 62,647 MILLION IS NOT MOSTLY OPERATING PROFIT. From its own release, verbatim: 'Second quarter 2026 net income includes NON-OPERATING PRE-TAX OTHER INCOME OF 53.4 BILLION, PRIMARILY FROM OUR INVESTMENTS IN ANTHROPIC.' ⚠️⚠️ I HAVE A DISCLOSED CONFLICT REGARDING ANTHROPIC - it is on file in this project. I report Amazon's own disclosure as written and take NO view on the valuation behind it; if this item ever drives a decision, Salee should ask someone with no stake. ⚠️ SET BESIDE THE OTHER AMAZON FACT ALREADY ON THIS BOARD: trailing-twelve-month FREE CASH FLOW IS NEGATIVE 7.6 BILLION. Record accounting profit and negative cash generation in the same company, in the same period. CASH DOES NOT LIE; NET INCOME CAN. Trailing-twelve-month GAAP net income is 135,281m, which would rank Amazon THIRD in America - not fifth as the circulating slide shows, because that slide uses Amazon's calendar 2025 figure of 77,670m. Budget unchanged at 48,000. RED FLAG: ⚠️ TRAILING-TWELVE-MONTH FREE CASH FLOW IS NOW NEGATIVE 7.6 BILLION, against POSITIVE 18.2 BILLION a year earlier - stated in Amazon's own Q2 2026 release. Operating cash flow was 161.4bn, up 33%, but purchases of property and equipment were 169.0bn. AND IT ISSUED 67.0 BILLION OF LONG-TERM DEBT IN THE FIRST HALF OF 2026 ALONE, taking long-term debt to 128.9bn. CFO Brian Olsavsky, verbatim, 30 July: 'You've seen us issue debt this year. We have a lot of options available to us as we continue to fund this growth.' ⚠️ THE CLAIM THAT AI CAPEX IS FUNDED FROM CASH FLOW RATHER THAN DEBT IS NO LONGER TRUE HERE. Guidance is about 220bn of cash capex in 2026, raised from about 200bn because of memory costs. + IN AMAZON'S FAVOUR ON THE HONESTY QUESTION: it is the only hyperscaler to SHORTEN depreciation life, cutting a subset of servers from SIX YEARS TO FIVE effective 1 Jan 2025, and saying why in its own 10-K: 'The shorter useful lives are due to the increased pace of technology development, particularly in the area of artificial intelligence and machine learning.' CEO Andy Jassy, 30 July 2026: 'The servers currently have a useful life of at least five to six years, and most of our AI capacity these days is being contracted for at least five-year terms.' Meta went the OTHER way with the same hardware. (new, not yet condensed) (5) WHAT CHANGES FOR US: NOTHING. NO BUDGET MOVES, NOTHING IS BOUGHT OR SOLD. Five of the seven are already core funded holdings - MSFT 58,000, GOOGL 78,000, NVDA 95,000, AAPL 24,000, AMZN 48,000, META 52,000, which is 355,000 of the 1,000,000 board in six of these seven names. Berkshire is not on ... (new, not yet condensed) ⚠️ WHAT ACTUALLY MATTERS TO US IS THE PUBLIC COUNTERPARTIES, AND HERE THE FINDINGS ARE REAL AND UNCOMFORTABLE. AMAZON'S Q2 2026 EARNINGS RELEASE DISCLOSES 53.4 BILLION OF NON-OPERATING PRE-TAX INCOME 'PRIMARILY FROM OUR INVESTMENTS IN ANTHROPIC' AGAINST OPERATING INCOME OF 27.5 BILLION - THE MARK ... (new, not yet condensed) 💡 SO WHAT DO WE OWN? THE INCUMBENT BEING ATTACKED (NVDA). THE WEAPON BEING USED AGAINST IT (AVGO 30,125.18 AND MRVL 7,872.66). ALL FOUR ATTACKERS (GOOGL, AMZN, MSFT, META - 200,195.14 BETWEEN THEM). AND THE GROUND THEY FIGHT ON (TSMC MAKES EVERY ONE OF THESE CHIPS WHOEVER DESIGNS THEM; MICRON SELLS ... (new, not yet condensed) 4. THE MAGNIFICENT-7 CASH CHART. ⚠️ APPLE IS NOT CASH-POOR AND THE CHART MEASURED THE WRONG LINE. Apple holds $146,517m of cash and marketable securities - SECOND OF THE SEVEN, not fifth - because $84,118m of it sits in LONG-TERM marketable securities that cash charts drop. Apple also returned ...
A8: GOOGL | B8: 2026-07-20 (Jul 20-26, 2026) | C8: MIXED | D8: + GOOGL is the book's quiet leader: +$15.6K of gain, more than the other six big holdings combined; only 13% off its high after a +12% YTD run - consolidation, not collapse. - Q2 (Jul 22) beat on headlines but free cash flow turned negative - capex outran $39.1B operating cash flow, $49.6B raised issuing equity; stock fell ~5-6% to the low $340s. - Capex is running ~42% of revenue and P/FCF is 72.5 and climbing; the fortress balance sheet (D/E 0.18) can afford it, but you are paying up while cash flow is impaired. + Bought the dip: +7 shares at ~$319.38 ($2,235.64) - now 205 shares at $269.88 avg cost, +17.7% unrealized; right instinct on a compounder whose Cloud is growing 82%. - Discipline flag: Dad's written limit was under $300 and the fill was $319, about 6% above the plan; the real add sits near $300 if the capex selloff continues. Weekly revision scan showed the Street's average GOOGL target drifting down 3.3%.
A9: GOOGL | B9: 2026-07-27 (Jul 27 - Aug 02, 2026) | C9: NEUTRAL | D9: Price could not be pinned down: a secondary page's $349.01 was distrusted after similar pages served stale data; the main page showed the Jul 30 close of $333.66.
A10: GOOGL | B10: 2026-08-03 (Aug 03-09, 2026) | C10: MIXED | D10: - Verdict: skip for now - GOOGL (with AMZN and MSFT) is 23-33% above Dad's limits with the smallest upside of the group. + Ranked #2 on the AI-beneficiary list: 8x engineering speed and falling AI serving cost (CEO-stated), $356.13 at Jul 31, 28.0x earnings, +20% upside, high confidence. Broker screen validated as a price source: POEMS 'Current Price' for GOOGL ($373.51, Aug 3) matched the official close to the cent.
A11: GOOGL | B11: 2026-08-10 (Aug 10-16, 2026) | C11: NEUTRAL | D11: (new, not yet condensed) Aug 11, 2026 · close — daily price refresh (run Aug 12, 00:30 UTC): 150 of 161 names advanced to the verified Aug 11 close (VECO was deleted upstream mid-run; its fetched close 50.16 discarded). Method per README: at-close quote pages with prev-close chain validated against history tables; ~20 ...
A12: GOOGL | B12: 2026-08-17 (Aug 17-23, 2026) | C12: NEUTRAL | D12: (new, not yet condensed) Aug 19, 2026 - close. CDNS and SNPS MOVED from SaaS to Computing Chips and placed side by side at the end of that group; both keep their existing prices, positions and budgets (CDNS 6 sh / 2,007.28 cost / 5,000 budget at the Aug 19 close of 314.98; SNPS watchlist-only at its Aug 17 price of ... (new, not yet condensed) Aug 19, 2026 - close. AEHR REPRICED from a stale Aug 17 quote of 145.61 to its verified Aug 19 close of 107.96 (-25.85% over two sessions: -15.36% Aug 18, -12.41% Aug 19). It closed 0.5% off the day's low on 2.9M shares - a full-day liquidation with no bounce - and 24/7 Wall St reported verbatim ... (new, not yet condensed) Aug 19, 2026 - close. CDNS BUDGET RAISED 5,000 -> 10,000 as instructed; at a cost of 2,007.28 that takes utilisation from 40.1% to 20.1% and headroom from 2,992.72 to 7,992.72. ALPHABET WAS NOT CHANGED: the instruction was to raise it TO 60,000 and it was ALREADY exactly 60,000, so there was ... (new, not yet condensed) Aug 19, 2026 - close. ALPHABET BUDGET RAISED 60,000 -> 70,000. At 59,475.92 of cost that takes utilisation from 99.1% to 84.97% and headroom from 524.08 to 10,524.08 - about 30 shares of room at the Aug 19 close of 344.72. GOOGL is 217 shares and 10.9% of the 686,813.04 book by market value; ... (new, not yet condensed) Aug 20, 2026 - close. BUDGET FIELDS RECONCILED - the last open item from the Aug 20 budget work. ORCL is CONFIRMED BY THE USER at 10,000, which is what the authoritative POS row already carried, so the dashboard was rendering it correctly all along; only the stale STOCKS mirror said 5,000 and it is ... (new, not yet condensed) Aug 20, 2026 - close. THREE CONVICTION BUDGETS RAISED to fund a staged 3-month programme: NVDA 80,000 -> 85,000 (+5,000), Alphabet 70,000 -> 80,000 (+10,000), TSM 50,000 -> 65,000 (+15,000). Headroom goes NVDA 2,659.04 -> 7,659.04, GOOGL 10,524.08 -> 20,524.08, TSM 10,078.47 -> 25,078.47. THE SKEW ...
... A468: SPCX | B468: 2026-09-14 (Sep 14-20, 2026) | C468: NEUTRAL | D468: ⚠️ THE 'AI IN SPACE' SLIDE - I HAVE NOT VERIFIED IT AND I WILL NOT PRETEND OTHERWISE. Two things are visible without research. FIRST, 'ELON JUST CONFIRMED' AND 'COULD LAUNCH' ARE DIFFERENT CLAIMS AND THE SLIDE USES BOTH IN THE SAME BREATH - a confirmation and a possibility are not the same thing. SECOND, ⚠️ ITS CLOSING COMPARISON '100 STARSHIP LAUNCHES = ANOTHER ANTHROPIC'S WORTH OF COMPUTE' INVOKES ANTHROPIC, WHICH MAKES ME - CONFLICT DISCLOSED - AND IS AN UNSOURCED CONVERSION BETWEEN TONNES OF HARDWARE AND A PRIVATE COMPANY'S COMPUTE FOOTPRINT THAT NOBODY HAS PUBLISHED. || 💡 THE ENGINEERING QUESTION THE SLIDE NEVER RAISES IS COOLING. A datacentre on Earth dumps its heat into air or water. A satellite can ONLY radiate heat away, which is far slower, and the slide's own picture shows solar panels rather than radiators. Anyone selling orbital datacentres has to answer that before the launch-cost arithmetic matters. ⚠️ NONE OF THIS CHANGES ANYTHING: SPCX IS UNFUNDED WITH NO BUDGET, ABOUT 1.3 BILLION SHARES UNLOCK IN NOVEMBER, AND THE DECISION IS 10 DECEMBER AFTER THE SECOND PUBLIC QUARTER. A slide about 2028 does not move a decision dated December 2026. ⚠️ TODAY'S WATCH ROW - STARSHIP FLIGHT 14, AND SALEE NEEDS TO DO NOTHING. NO BUDGET, NO SHARES, NO ORDER. The row is information-gathering only. WHAT TO LOOK FOR: whether the SUPER HEAVY BOOSTER survives. On Flight 13 (24 July) the ship already worked - 20 Starlink V3 satellites deployed and a first intact splashdown - while the booster relit only 10 engines and was destroyed on water impact. A clean booster removes a known risk; it does NOT revalue a 2-trillion-dollar company. ⚠️ AND IF THE LAUNCH SLIPS, THAT IS NORMAL - the date came from an FCC filing marked NET, 'no earlier than'. The real decisions are 5 NOVEMBER (second public quarter) and 10 DECEMBER (whether to assign a budget at all), and the 1.3 BILLION share lock-up release in November sits between them. Nothing about a launch outcome moves those dates. (new, not yet condensed) (B) THE SPACEX 'AI IN SPACE' SLIDE - ⚠️ I HAVE NOT VERIFIED IT AND I WILL NOT PRETEND OTHERWISE. What I can say without research: 'ELON JUST CONFIRMED' and 'COULD LAUNCH' are two different claims and the slide uses both. ⚠️ AND ITS CLOSING COMPARISON - '100 STARSHIP LAUNCHES = ANOTHER ANTHROPIC'S ... (new, not yet condensed) ⚠️⚠️ AND THE MOST IMPORTANT THING ON THE WHOLE SLIDE IS THE NAME SALEE HAS NEVER HEARD OF: CXMT AT 545 BILLION IS REAL, AND IT MATTERS TO OUR MICRON DECISION IN FIFTEEN DAYS. ChangXin Memory Technologies LISTED ON THE SHANGHAI STAR MARKET ON 27 JULY 2026 under ticker 688825, rose 531% on debut to a ... (new, not yet condensed) ⚠️ TWO FACTUAL ERRORS ON THE SLIDE. FIRST, IT LISTS SPACEX AS 'PRIVATE'. SPACEX LISTED ON 12 JUNE 2026 AT 135 DOLLARS AND TRADES AS SPCX - it is on our board, unfunded, with the decision dated 10 DECEMBER after the November lock-up. Second, it presents COINBASE as a leader shaping the future. ⚠️ ... (new, not yet condensed) ON THE TEN NAMES THEMSELVES: ONLY TWO ACTUALLY MAKE MONEY - NOW AT AN 11.34% NET MARGIN AND ORCL AT 26.36%, AND ⚠️ ORACLE'S RULE OF 40 READS MINUS 18.4 BECAUSE FREE CASH FLOW HAS GONE NEGATIVE FUNDING DATA CENTRES. ASTS TRADES AT 203x SALES ON ALMOST NO REVENUE. SPCX AT 81x SALES WHILE BURNING ...

Sheet Full Log
A1: Ticker | B1: Date | C1: Source | D1: Comment
A2: AAOI | B2: 2026-07-22 | C2: Claude - chat | D2: Everything is reconciled and re-deployed — dashboard, workbook, dad's link, sidebar artifact, and your P4 folder all now tie to the POEMS statement to the cent: cost $536,988.31, MV $635,013.32, +18.25%. AAOI is also in (details below).
A3: AAOI | B3: 2026-07-22 | C3: Claude - chat | D3: So where were you looking? Two possibilities: if it was the sidebar artifact or the local P4 file, it may have been open from before the update — close and reopen, and you should see "Fundamentals as of Jul 22, 2026 (POEMS statement, intraday)" with 58 names including CDNS and AAOI. If it was dad's GitHub link, the code is pushed (I confirmed the repo head), but GitHub Pages' CDN caches for ~10 minutes — I just checked and it was still serving the previous build; a hard refresh (Cmd+Shift+R) in a few minutes will pull the reconciled one.
A4: AAOI | B4: 2026-07-22 | C4: Claude - chat | D4: For a memory maker, the largest single cost of a wafer isn't a purchased material at all — it's depreciation on the fab equipment (roughly 40–50% of cost of goods for leading-edge DRAM). The machines from Applied Materials, Lam, KLA, ASML and Tokyo Electron *are* the "raw material" of a modern fab in economic terms. Purchased materials in aggregate run only ~25–30%, and that basket is fragmented across many consumables (Silicon Analysts (https://siliconanalysts.com/guide/semiconductor-costs)):
A5: AAOI | B5: 2026-07-22 | C5: Claude - chat | D5: ⚠ The whole gap is one row: CRWD — the July 2026 4-for-1 stock split was never applied to your manual record.
A6: AAOI | B6: 2026-07-23 | C6: Claude - chat | D6: On your naming request — I applied my recommendations and here's the reasoning, all easy to revert if any miss:
A7: AAOI | B7: 2026-07-25 | C7: Claude - chat | D7: One flag for your own records: I applied the standard $8.56 POEMS commission on this fill (same rate we standardized in the reconciliation). If your trade confirmation shows a different fee, tell me and I'll true up the cost basis to the cent.
A8: AAOI | B8: 2026-07-25 | C8: Claude - chat | D8: Three AI-datacenter / crypto-miner neocloud names — APLD (Applied Digital), CIFR (Cipher Mining), HUT (Hut 8) — into the Neocloud group (g=13, alongside IREN/NBIS/CRWV). Pulling their fundamentals.
A9: AAOI | B9: 2026-07-25 | C9: Claude - chat | D9: | APLD | Applied Digital | $27.19 | −42% | +112% | −59% | 1.10 | Signed hyperscaler leases; heavy capex build |
A10: AAOI | B10: 2026-07-31 | C10: Claude - chat | D10: Stagger applied — earnings job now 03:00 UTC, clear of the 01:00 pile-up. Now the staleness marker.
A11: AAOI | B11: 2026-08-03 | C11: Claude - chat | D11: 3–6. Your handwritten note is applied. AEHR moved to Chips Manufacturing. DELL, HPE and SMCI moved into Neocloud Watch, joined by NOK. POET went into Photonic & Optic Fiber, AMPX into Energy. That's 110 names now, all priced at the July 31 close. Live at https://sakulratpradit.github.io/p4-trrsg5/
A12: AAOI | B12: 2026-08-05 | C12: Claude - chat | D12: Your six buys from last night are in. FN 3 sh @ $532.00, LITE 2 sh @ $854.68, META 3.5 sh @ $583.24, COHR 4 sh @ $330.00, AAOI 10 sh @ $133.00 — $8,039.48 total. Every fill price was reverse-engineered from the cash amounts, and they all came out to clean round limit prices with a flat $8.56 commission, which is exactly what POEMS charges. Your new cost basis of $560,431.70 matches the POEMS statement to the cent.
... A2309: ZETA | B2309: 2026-09-17 | C2309: Dashboard note d77362b | D2309: ⚠️ FOUR OF SIX ROSE AFTER WE SOLD, ONE BY 42.7%. BUT THE DATES SHOW WHAT REALLY HAPPENED: NOW, CRWV, ORCL AND NBIS ALL WENT IN A SIX-DAY WINDOW IN JULY. THAT WAS ONE RESTRUCTURE DECISION TO RAISE CASH, NOT SIX STOCK DECISIONS. THE TWO GENUINE INDIVIDUAL SELLS, BOTH IN SEPTEMBER, WERE BOTH RIGHT - ONDS DOWN 4.2% SINCE WE LEFT, ZETA BANKED AT PLUS 71.2% AND FLAT SINCE. 💡 OUR STOCK JUDGEMENT HAS BEEN GOOD. OUR CASH-RAISING WAS EXPENSIVE.

Sheet Dashboard Notes
A1: Date | B1: Commit | C1: Note stored in the dashboard
A2: 2026-07-21 | B2: 9cf0e91 | C2: Jul 17, 2026 (US close)
A3: 2026-07-21 | B3: 38633c9 | C3: Jul 20, 2026 (US close)
A4: 2026-07-22 | B4: 724110b | C4: Jul 21, 2026 (US close)
A5: 2026-07-22 | B5: 3db7062 | C5: Jul 22, 2026 (POEMS statement, intraday)
A6: 2026-07-23 | B6: ae9cd28 | C6: Jul 22, 2026 (US close · POEMS Jul 23)
A7: 2026-07-24 | B7: e0e44f5 | C7: Jul 24, 2026 (POEMS live)
A8: 2026-07-25 | B8: eba49cb | C8: Jul 24, 2026 (US close)
A9: 2026-07-25 | B9: 57636d3 | C9: Jul 25, 2026 (POEMS live)
A10: 2026-07-28 | B10: c1539a0 | C10: Jul 27, 2026 (POEMS live)
A11: 2026-07-28 | B11: 9bb615d | C11: Jul 27, 2026 (US close)
A12: 2026-07-28 | B12: c7b35f2 | C12: Jul 28, 2026 (POEMS reconciled)
... A1085: 2026-09-19 | B1085: 6ef4da5 | C1085: PREVIOUS ENTRY: Sep 19, 2026 (3) - 🎯 BIOTECH: INTERESTING AS A FIELD, WRONG FOR THIS BOARD AS BUILT - AND CHECKING IT FOUND THAT GROUP 7 IS MISNAMED. ONLY 1 OF THE 18 NAMES IS ON OUR BOARD: TEMPUS AI, WITH NO BUDGET AND A MINUS 17.77% NET MARGIN.

Sheet Our Notes
A1: Date | B1: Who | C1: Ticker | D1: Our note / question | E1: Action agreed | F1: Done?
A2: 2026-08-07 | B2: Salee | C2: NVDA | D2: EXAMPLE ROW - delete me. Dad wants to add on any dip under 210; check budget headroom first. | E2: Wait for 210 or lower, then buy up to budget. | F2: No
A4: This sheet belongs to Salee and Dad. Claude reads it back and copies it forward every time the workbook is rebuilt, so nothing typed here is ever lost.

Sheet Follow-ups
A1: Ticker | B1: Type | C1: Open item | D1: Raised
A2: ZETA | B2: Data error | C2: Stored all-time high 25.95 is BELOW the stored price 27.07 and below the sourced 52-week high 28.50 - impossible. 52-week low should be 14.37 (stored 12.10) and high 28.50 (stored 27.07). Needs a sourced ATH before it can be fixed; Claude will not guess it. | D2: 2026-08-06
A3: AIRJ | B3: Data check | C3: Stored all-time high 29.27 conflicts with a researcher figure of 49.11 (Mar 11 2024, TradingView). TradingView is on the unreliable list, so a second source is needed before changing anything. | D3: 2026-08-05
A4: APP | B4: Data gap | C4: Capital expenditure is stored blank. Fill it if a source turns up. | D4: 2026-08-05
A5: SKHY | B5: Stale data | C5: Fundamentals are pre-Q2 and therefore flattering. Budget left about $8,087. | D5: 2026-08-04
A6: LWLG / AXTI | B6: Chart scale | C6: Absurd-scale valuations distort three charts: LWLG price-to-sales 5,040x, AXTI price-to-earnings 957x and EV/EBITDA 1,042x. Claude has offered to cap the display scale so the other bars stay readable - awaiting a yes. | D6: 2026-08-06
A7: AXTI | B7: Risk to watch | C7: Beijing Tongmei withdrew its Shanghai STAR Market listing on Jul 8 2026, triggering redemption rights on about US$49M held by eleven private-equity funds. Company says it has the cash. | D7: 2026-08-06
A8: COHR | B8: Earnings | C8: Reports FY26 Q4 and full year on Aug 12, 2026. | D8: 2026-08-05
A9: LWLG | B9: Earnings | C9: Reports Q2 on Aug 11, 2026 (company-confirmed). | D9: 2026-08-05
A10: NVDA | B10: Earnings | C10: Reports Q2 FY2027 on Aug 26, 2026 (company-confirmed). Budget headroom about $2,668, roughly 12 shares. | D10: 2026-08-06
A11: AIRJ | B11: Earnings | C11: Next earnings estimated Aug 21, 2026 - NOT company-confirmed. | D11: 2026-08-05
A12: AXTI | B12: Earnings | C12: Next earnings date could not be found and is not company-confirmed. | D12: 2026-08-06
... A20: Portfolio | B20: Open offer | C20: Claude has offered but not yet built: a dividends-received tally, a speculative-watch screen, per-name budgets for Fintech/Digital Platform, a manual price-entry box on the dashboard, and a poster version without profit-and-loss for showing Dad. | D20: 2026-08-04
